Workbook

Sheet README
A1: PII / PHI Enterprise Entity Policy Taxonomy
A2: Candidate taxonomy for the Document Intelligence detection pipeline — MUST_HAVE / NICE_TO_HAVE / DROP
A4: SCOPE & METHOD
A5: - This workbook was built directly from the brief supplied in this engagement. No existing teammate workbook/candidate taxonomy file was attached to this conversation, so there was no prior candidate taxonomy to validate against — this workbook is the first-pass candidate itself and should be reviewed by an SME before production use (see 'Reviewed Status' column).
A6: - Regulatory citations use only the official source URLs supplied in the brief (HHS/HIPAA, EUR-Lex/GDPR, PCI SSC, NIST, FTC, MeitY/India DPDP). Where a precise citation was not present in the supplied source set (e.g., GDPR Art. 10 on criminal-offense data, 42 CFR Part 2, US FCRA, IRS Publication 4812), that gap is flagged explicitly in the Notes column and the row's Regulation Type is marked INFERENCE or RISK-BASED RECOMMENDATION rather than REGULATORY REQUIREMENT.
A7: - No company/client policy document was supplied for this engagement. Every row's Company Policy column reads 'Company policy evidence not supplied.' as instructed — no internal policy has been invented.
A8: - 27 document types across Healthcare, Financial, Corporate/HR, Legal/Business, Identity, Security/Technical, and Generic categories are covered, per the brief's required scope.
A10: REGULATION TYPE LEGEND (used in Master_Entity_Policy, column K context)
A11: - REGULATORY REQUIREMENT: a binding legal obligation under the cited law/regulation, for the stated jurisdiction.
A12: - STANDARD/CONTROL: an industry standard or risk-management framework (e.g., PCI DSS, NIST SP 800-122) rather than a statute.
A13: - RISK-BASED RECOMMENDATION: not explicitly enumerated by a cited regulation in the supplied source set; classified using breach-impact reasoning.
A14: - INFERENCE: the closest available citation in the supplied source set does not squarely cover this entity (the precise citation is named in Rationale/Notes); verify independently before relying on it.
... A33: - See the accompanying change summary for full before/after counts and items flagged for SME review.

Sheet Master_Entity_Policy
A1: Document Type | B1: Business Workflow | C1: Entity | D1: Canonical Entity Type | E1: Category | F1: Data Type (PII/PHI/Financial/Payment/Credential/Other) | G1: Priority | H1: Risk Level | I1: Threat if Exposed | J1: Regulation | K1: Regulation Section / Article / Requirement | L1: Jurisdiction | M1: Evidence URL | N1: Classification Basis | O1: Evidence Type | P1: Confidence in Classification
A2: Medical Record / Clinical Note | B2: Ongoing clinical documentation of a patient's encounters, diagnoses, and treatment to support continuity of care. | C2: Full Name / Person Name | D2: Full Name / Person Name | E2: Direct Identifier | F2: PII | G2: MUST_HAVE | H2: CRITICAL | I2: Re-identifies an individual's health record; enables medical-identity theft and targeted harassment. | J2: HIPAA Privacy Rule | K2: 45 CFR 164.514(b)(2) — Safe Harbor identifier list | L2: United States — HIPAA covered entities & business associates | M2: https://www.hhs.gov/hipaa/for-professionals/special-topics/de-identification/index.html | N2: REGULATION | O2: Explicitly protected identifier | P2: MEDIUM
A3: Medical Record / Clinical Note | B3: Ongoing clinical documentation of a patient's encounters, diagnoses, and treatment to support continuity of care. | C3: Date of Birth | D3: Date of Birth | E3: Direct Identifier | F3: PII | G3: MUST_HAVE | H3: HIGH | I3: HIPAA Safe Harbor identifier; strengthens patient re-identification when combined with other fields. | J3: HIPAA Privacy Rule | K3: 45 CFR 164.514(b)(2) — Safe Harbor identifier list | L3: United States — HIPAA covered entities & business associates | M3: https://www.hhs.gov/hipaa/for-professionals/special-topics/de-identification/index.html | N3: REGULATION | O3: Explicitly protected identifier | P3: MEDIUM
A4: Medical Record / Clinical Note | B4: Ongoing clinical documentation of a patient's encounters, diagnoses, and treatment to support continuity of care. | C4: Medical Record Number (MRN) | D4: Medical Record Number (MRN) | E4: Direct Identifier | F4: PHI | G4: MUST_HAVE | H4: CRITICAL | I4: Directly links an individual to their entire clinical history; enables medical-identity theft and insurance fraud. | J4: HIPAA Privacy Rule | K4: 45 CFR 164.514(b)(2)(I) — Medical record numbers | L4: United States — HIPAA covered entities | M4: https://www.hhs.gov/hipaa/for-professionals/special-topics/de-identification/index.html | N4: REGULATION | O4: PHI / health information | P4: HIGH
A5: Medical Record / Clinical Note | B5: Ongoing clinical documentation of a patient's encounters, diagnoses, and treatment to support continuity of care. | C5: Street / Mailing Address | D5: Street / Mailing Address | E5: Direct Identifier | F5: PII | G5: MUST_HAVE | H5: HIGH | I5: HIPAA Safe Harbor identifier; discloses where a patient lives, raising both privacy and physical-safety risk. | J5: HIPAA Privacy Rule | K5: 45 CFR 164.514(b)(2) — Safe Harbor identifier list | L5: United States — HIPAA covered entities & business associates | M5: https://www.hhs.gov/hipaa/for-professionals/special-topics/de-identification/index.html | N5: REGULATION | O5: Explicitly protected identifier | P5: MEDIUM
A6: Medical Record / Clinical Note | B6: Ongoing clinical documentation of a patient's encounters, diagnoses, and treatment to support continuity of care. | C6: Phone Number | D6: Phone Number | E6: Direct Identifier | F6: PII | G6: MUST_HAVE | H6: MEDIUM | I6: HIPAA Safe Harbor identifier; enables phishing/social engineering against a patient. | J6: HIPAA Privacy Rule | K6: 45 CFR 164.514(b)(2) — Safe Harbor identifier list | L6: United States — HIPAA covered entities & business associates | M6: https://www.hhs.gov/hipaa/for-professionals/special-topics/de-identification/index.html | N6: REGULATION | O6: Explicitly protected identifier | P6: MEDIUM
A7: Medical Record / Clinical Note | B7: Ongoing clinical documentation of a patient's encounters, diagnoses, and treatment to support continuity of care. | C7: Diagnosis / Medical Condition | D7: Diagnosis / Medical Condition | E7: Health/Clinical Data | F7: PHI | G7: MUST_HAVE | H7: CRITICAL | I7: Discrimination, stigmatization, employment/insurance harm, and medical-privacy harm if disclosed. | J7: HIPAA Privacy Rule | K7: 45 CFR 160.103 — Protected Health Information definition | L7: United States — HIPAA covered entities | M7: https://www.hhs.gov/hipaa/for-professionals/special-topics/de-identification/index.html | N7: REGULATION | O7: PHI / health information | P7: HIGH
A8: Medical Record / Clinical Note | B8: Ongoing clinical documentation of a patient's encounters, diagnoses, and treatment to support continuity of care. | C8: Procedure Code / Description | D8: Procedure Code / Description | E8: Health/Clinical Data | F8: PHI | G8: NICE_TO_HAVE | H8: MEDIUM | I8: Discloses treatment history; can imply a condition (re-identification risk) and support insurance fraud. | J8: HIPAA Privacy Rule | K8: 45 CFR 160.103 — PHI definition | L8: United States — HIPAA covered entities | M8: https://www.hhs.gov/hipaa/for-professionals/special-topics/de-identification/index.html | N8: REGULATION | O8: PHI / health information | P8: MEDIUM
A9: Medical Record / Clinical Note | B9: Ongoing clinical documentation of a patient's encounters, diagnoses, and treatment to support continuity of care. | C9: Medication / Prescription Detail | D9: Medication / Prescription Detail | E9: Health/Clinical Data | F9: PHI | G9: MUST_HAVE | H9: HIGH | I9: Can reveal a sensitive condition by inference (e.g., psychiatric, HIV, oncology drugs); enables prescription fraud. | J9: HIPAA Privacy Rule | K9: 45 CFR 160.103 — PHI definition | L9: United States — HIPAA covered entities | M9: https://www.hhs.gov/hipaa/for-professionals/special-topics/de-identification/index.html | N9: REGULATION | O9: PHI / health information | P9: HIGH
A10: Medical Record / Clinical Note | B10: Ongoing clinical documentation of a patient's encounters, diagnoses, and treatment to support continuity of care. | C10: Clinical Notes / Narrative | D10: Clinical Notes / Narrative | E10: Health/Clinical Data | F10: PHI | G10: MUST_HAVE | H10: CRITICAL | I10: Free text frequently contains multiple PHI elements at once (identity + diagnosis + history); high aggregate breach impact. | J10: HIPAA Privacy Rule | K10: 45 CFR 160.103 — PHI definition | L10: United States — HIPAA covered entities | M10: https://www.hhs.gov/hipaa/for-professionals/special-topics/de-identification/index.html | N10: REGULATION | O10: PHI / health information | P10: HIGH
A11: Medical Record / Clinical Note | B11: Ongoing clinical documentation of a patient's encounters, diagnoses, and treatment to support continuity of care. | C11: Allergy Information | D11: Allergy Information | E11: Health/Clinical Data | F11: PHI | G11: NICE_TO_HAVE | H11: MEDIUM | I11: Reveals health information; misuse risk lower than diagnosis but still privacy-sensitive. | J11: HIPAA Privacy Rule | K11: 45 CFR 160.103 — PHI definition | L11: United States — HIPAA covered entities | M11: https://www.hhs.gov/hipaa/for-professionals/special-topics/de-identification/index.html | N11: REGULATION | O11: PHI / health information | P11: MEDIUM
A12: Medical Record / Clinical Note | B12: Ongoing clinical documentation of a patient's encounters, diagnoses, and treatment to support continuity of care. | C12: Treating Provider Name / NPI Number | D12: Treating Provider Name / NPI Number | E12: Direct Identifier | F12: PHI | G12: NICE_TO_HAVE | H12: MEDIUM | I12: Discloses the treating clinician; can support social engineering against the practice, lower risk to the patient directly. | J12: HIPAA Privacy Rule | K12: 45 CFR 164.514(b)(2) — related identifiers | L12: United States — HIPAA covered entities | M12: https://www.hhs.gov/hipaa/for-professionals/special-topics/de-identification/index.html | N12: REGULATION | O12: PHI / health information | P12: MEDIUM
... A23: Lab Report / Pathology Report | B23: Laboratory or pathology testing and result reporting to support diagnosis and treatment decisions. | C23: Admission / Discharge / Service Date | D23: Admission / Discharge / Service Date | E23: Direct Identifier | F23: PHI | G23: MUST_HAVE | H23: MEDIUM | I23: Enables re-identification when correlated with public event data (e.g., accident reports); listed HIPAA identifier. | J23: HIPAA Privacy Rule | K23: 45 CFR 164.514(b)(2)(I) — All elements of dates related to an individual | L23: United States — HIPAA covered entities | M23: https://www.hhs.gov/hipaa/for-professionals/special-topics/de-identification/index.html | N23: REGULATION | O23: PHI / health information | P23: HIGH
A24: Lab Report / Pathology Report | B24: Laboratory or pathology testing and result reporting to support diagnosis and treatment decisions. | C24: Medical Equipment/Instrument Serial Number | D24: Medical Equipment/Instrument Serial Number | E24: Administrative/Structural Metadata | F24: Other | G24: DROP | I24: None — identifies a machine/asset, not a person; occasionally relevant to biomedical-device recall workflows but not a privacy target. | J24: N/A | K24: N/A | L24: N/A | N24: CONTEXTUAL | O24: Low-value technical field | P24: MEDIUM
A25: Prescription | B25: Prescribing and dispensing of medication to a patient. | C25: Full Name / Person Name | D25: Full Name / Person Name | E25: Direct Identifier | F25: PII | G25: MUST_HAVE | H25: CRITICAL | I25: Re-identifies an individual's health record; enables medical-identity theft and targeted harassment. | J25: HIPAA Privacy Rule | K25: 45 CFR 164.514(b)(2) — Safe Harbor identifier list | L25: United States — HIPAA covered entities & business associates | M25: https://www.hhs.gov/hipaa/for-professionals/special-topics/de-identification/index.html | N25: REGULATION | O25: Explicitly protected identifier | P25: MEDIUM
A26: Prescription | B26: Prescribing and dispensing of medication to a patient. | C26: Date of Birth | D26: Date of Birth | E26: Direct Identifier | F26: PII | G26: MUST_HAVE | H26: HIGH | I26: HIPAA Safe Harbor identifier; strengthens patient re-identification when combined with other fields. | J26: HIPAA Privacy Rule | K26: 45 CFR 164.514(b)(2) — Safe Harbor identifier list | L26: United States — HIPAA covered entities & business associates | M26: https://www.hhs.gov/hipaa/for-professionals/special-topics/de-identification/index.html | N26: REGULATION | O26: Explicitly protected identifier | P26: MEDIUM
A27: Prescription | B27: Prescribing and dispensing of medication to a patient. | C27: Street / Mailing Address | D27: Street / Mailing Address | E27: Direct Identifier | F27: PII | G27: MUST_HAVE | H27: HIGH | I27: HIPAA Safe Harbor identifier; discloses where a patient lives, raising both privacy and physical-safety risk. | J27: HIPAA Privacy Rule | K27: 45 CFR 164.514(b)(2) — Safe Harbor identifier list | L27: United States — HIPAA covered entities & business associates | M27: https://www.hhs.gov/hipaa/for-professionals/special-topics/de-identification/index.html | N27: REGULATION | O27: Explicitly protected identifier | P27: MEDIUM
A28: Prescription | B28: Prescribing and dispensing of medication to a patient. | C28: Medication / Prescription Detail | D28: Medication / Prescription Detail | E28: Health/Clinical Data | F28: PHI | G28: MUST_HAVE | H28: HIGH | I28: Can reveal a sensitive condition by inference (e.g., psychiatric, HIV, oncology drugs); enables prescription fraud. | J28: HIPAA Privacy Rule | K28: 45 CFR 160.103 — PHI definition | L28: United States — HIPAA covered entities | M28: https://www.hhs.gov/hipaa/for-professionals/special-topics/de-identification/index.html | N28: REGULATION | O28: PHI / health information | P28: HIGH
A29: Prescription | B29: Prescribing and dispensing of medication to a patient. | C29: Treating Provider Name / NPI Number | D29: Treating Provider Name / NPI Number | E29: Direct Identifier | F29: PHI | G29: NICE_TO_HAVE | H29: MEDIUM | I29: Discloses the treating clinician; can support social engineering against the practice, lower risk to the patient directly. | J29: HIPAA Privacy Rule | K29: 45 CFR 164.514(b)(2) — related identifiers | L29: United States — HIPAA covered entities | M29: https://www.hhs.gov/hipaa/for-professionals/special-topics/de-identification/index.html | N29: REGULATION | O29: PHI / health information | P29: MEDIUM
A30: Prescription | B30: Prescribing and dispensing of medication to a patient. | C30: Medical Record Number (MRN) | D30: Medical Record Number (MRN) | E30: Direct Identifier | F30: PHI | G30: MUST_HAVE | H30: CRITICAL | I30: Directly links an individual to their entire clinical history; enables medical-identity theft and insurance fraud. | J30: HIPAA Privacy Rule | K30: 45 CFR 164.514(b)(2)(I) — Medical record numbers | L30: United States — HIPAA covered entities | M30: https://www.hhs.gov/hipaa/for-professionals/special-topics/de-identification/index.html | N30: REGULATION | O30: PHI / health information | P30: HIGH
A31: Prescription | B31: Prescribing and dispensing of medication to a patient. | C31: Signature | D31: Signature | E31: Direct Identifier | F31: PII | G31: NICE_TO_HAVE | H31: MEDIUM | I31: Enables forgery of authorization for treatment or disclosure. | J31: HIPAA Privacy Rule | K31: 45 CFR 164.514(b)(2) — Safe Harbor identifier list | L31: United States — HIPAA covered entities & business associates | M31: https://www.hhs.gov/hipaa/for-professionals/special-topics/de-identification/index.html | N31: REGULATION | O31: Explicitly protected identifier | P31: MEDIUM
A32: Prescription | B32: Prescribing and dispensing of medication to a patient. | C32: Health Insurance Policy Number | D32: Health Insurance Policy Number | E32: Direct Identifier | F32: PHI | G32: MUST_HAVE | H32: HIGH | I32: Enables fraudulent insurance claims and unauthorized access to coverage details. | J32: HIPAA Privacy Rule | K32: 45 CFR 164.514(b)(2)(I) — Health plan beneficiary numbers | L32: United States — HIPAA covered entities | M32: https://www.hhs.gov/hipaa/for-professionals/special-topics/de-identification/index.html | N32: REGULATION | O32: PHI / health information | P32: HIGH
A33: Discharge Summary | B33: Summary of a patient's hospital stay, treatment, and follow-up plan at the point of discharge. | C33: Full Name / Person Name | D33: Full Name / Person Name | E33: Direct Identifier | F33: PII | G33: MUST_HAVE | H33: CRITICAL | I33: Re-identifies an individual's health record; enables medical-identity theft and targeted harassment. | J33: HIPAA Privacy Rule | K33: 45 CFR 164.514(b)(2) — Safe Harbor identifier list | L33: United States — HIPAA covered entities & business associates | M33: https://www.hhs.gov/hipaa/for-professionals/special-topics/de-identification/index.html | N33: REGULATION | O33: Explicitly protected identifier | P33: MEDIUM
A34: Discharge Summary | B34: Summary of a patient's hospital stay, treatment, and follow-up plan at the point of discharge. | C34: Date of Birth | D34: Date of Birth | E34: Direct Identifier | F34: PII | G34: MUST_HAVE | H34: HIGH | I34: HIPAA Safe Harbor identifier; strengthens patient re-identification when combined with other fields. | J34: HIPAA Privacy Rule | K34: 45 CFR 164.514(b)(2) — Safe Harbor identifier list | L34: United States — HIPAA covered entities & business associates | M34: https://www.hhs.gov/hipaa/for-professionals/special-topics/de-identification/index.html | N34: REGULATION | O34: Explicitly protected identifier | P34: MEDIUM
A35: Discharge Summary | B35: Summary of a patient's hospital stay, treatment, and follow-up plan at the point of discharge. | C35: Medical Record Number (MRN) | D35: Medical Record Number (MRN) | E35: Direct Identifier | F35: PHI | G35: MUST_HAVE | H35: CRITICAL | I35: Directly links an individual to their entire clinical history; enables medical-identity theft and insurance fraud. | J35: HIPAA Privacy Rule | K35: 45 CFR 164.514(b)(2)(I) — Medical record numbers | L35: United States — HIPAA covered entities | M35: https://www.hhs.gov/hipaa/for-professionals/special-topics/de-identification/index.html | N35: REGULATION | O35: PHI / health information | P35: HIGH
A36: Discharge Summary | B36: Summary of a patient's hospital stay, treatment, and follow-up plan at the point of discharge. | C36: Diagnosis / Medical Condition | D36: Diagnosis / Medical Condition | E36: Health/Clinical Data | F36: PHI | G36: MUST_HAVE | H36: CRITICAL | I36: Discrimination, stigmatization, employment/insurance harm, and medical-privacy harm if disclosed. | J36: HIPAA Privacy Rule | K36: 45 CFR 160.103 — Protected Health Information definition | L36: United States — HIPAA covered entities | M36: https://www.hhs.gov/hipaa/for-professionals/special-topics/de-identification/index.html | N36: REGULATION | O36: PHI / health information | P36: HIGH
... A49: Imaging / Radiology Report | B49: Interpretation and reporting of diagnostic imaging studies (X-ray, CT, MRI, ultrasound). | C49: Admission / Discharge / Service Date | D49: Admission / Discharge / Service Date | E49: Direct Identifier | F49: PHI | G49: MUST_HAVE | H49: MEDIUM | I49: Enables re-identification when correlated with public event data (e.g., accident reports); listed HIPAA identifier. | J49: HIPAA Privacy Rule | K49: 45 CFR 164.514(b)(2)(I) — All elements of dates related to an individual | L49: United States — HIPAA covered entities | M49: https://www.hhs.gov/hipaa/for-professionals/special-topics/de-identification/index.html | N49: REGULATION | O49: PHI / health information | P49: HIGH
A50: Imaging / Radiology Report | B50: Interpretation and reporting of diagnostic imaging studies (X-ray, CT, MRI, ultrasound). | C50: CT Number / Imaging Technical Parameter | D50: CT Number / Imaging Technical Parameter | E50: Administrative/Structural Metadata | F50: Other | G50: DROP | I50: None — a physical measurement/scanner calibration value, not a personal identifier or health-status disclosure. | J50: N/A | K50: N/A | L50: N/A | N50: CONTEXTUAL | O50: Low-value technical field | P50: HIGH
A51: Imaging / Radiology Report | B51: Interpretation and reporting of diagnostic imaging studies (X-ray, CT, MRI, ultrasound). | C51: Medical Equipment/Instrument Serial Number | D51: Medical Equipment/Instrument Serial Number | E51: Administrative/Structural Metadata | F51: Other | G51: DROP | I51: None — identifies a machine/asset, not a person; occasionally relevant to biomedical-device recall workflows but not a privacy target. | J51: N/A | K51: N/A | L51: N/A | N51: CONTEXTUAL | O51: Low-value technical field | P51: MEDIUM
A52: Patient Registration / Referral | B52: Intake and registration of a new patient, or referral of a patient between providers. | C52: Full Name / Person Name | D52: Full Name / Person Name | E52: Direct Identifier | F52: PII | G52: MUST_HAVE | H52: CRITICAL | I52: Re-identifies an individual's health record; enables medical-identity theft and targeted harassment. | J52: HIPAA Privacy Rule | K52: 45 CFR 164.514(b)(2) — Safe Harbor identifier list | L52: United States — HIPAA covered entities & business associates | M52: https://www.hhs.gov/hipaa/for-professionals/special-topics/de-identification/index.html | N52: REGULATION | O52: Explicitly protected identifier | P52: MEDIUM
A53: Patient Registration / Referral | B53: Intake and registration of a new patient, or referral of a patient between providers. | C53: Date of Birth | D53: Date of Birth | E53: Direct Identifier | F53: PII | G53: MUST_HAVE | H53: HIGH | I53: HIPAA Safe Harbor identifier; strengthens patient re-identification when combined with other fields. | J53: HIPAA Privacy Rule | K53: 45 CFR 164.514(b)(2) — Safe Harbor identifier list | L53: United States — HIPAA covered entities & business associates | M53: https://www.hhs.gov/hipaa/for-professionals/special-topics/de-identification/index.html | N53: REGULATION | O53: Explicitly protected identifier | P53: MEDIUM
A54: Patient Registration / Referral | B54: Intake and registration of a new patient, or referral of a patient between providers. | C54: Street / Mailing Address | D54: Street / Mailing Address | E54: Direct Identifier | F54: PII | G54: MUST_HAVE | H54: HIGH | I54: HIPAA Safe Harbor identifier; discloses where a patient lives, raising both privacy and physical-safety risk. | J54: HIPAA Privacy Rule | K54: 45 CFR 164.514(b)(2) — Safe Harbor identifier list | L54: United States — HIPAA covered entities & business associates | M54: https://www.hhs.gov/hipaa/for-professionals/special-topics/de-identification/index.html | N54: REGULATION | O54: Explicitly protected identifier | P54: MEDIUM
A55: Patient Registration / Referral | B55: Intake and registration of a new patient, or referral of a patient between providers. | C55: Phone Number | D55: Phone Number | E55: Direct Identifier | F55: PII | G55: MUST_HAVE | H55: MEDIUM | I55: HIPAA Safe Harbor identifier; enables phishing/social engineering against a patient. | J55: HIPAA Privacy Rule | K55: 45 CFR 164.514(b)(2) — Safe Harbor identifier list | L55: United States — HIPAA covered entities & business associates | M55: https://www.hhs.gov/hipaa/for-professionals/special-topics/de-identification/index.html | N55: REGULATION | O55: Explicitly protected identifier | P55: MEDIUM
A56: Patient Registration / Referral | B56: Intake and registration of a new patient, or referral of a patient between providers. | C56: Email Address | D56: Email Address | E56: Direct Identifier | F56: PII | G56: MUST_HAVE | H56: MEDIUM | I56: HIPAA Safe Harbor identifier; a credential-adjacent identifier usable for phishing tied to health context. | J56: HIPAA Privacy Rule | K56: 45 CFR 164.514(b)(2) — Safe Harbor identifier list | L56: United States — HIPAA covered entities & business associates | M56: https://www.hhs.gov/hipaa/for-professionals/special-topics/de-identification/index.html | N56: REGULATION | O56: Explicitly protected identifier | P56: MEDIUM
A57: Patient Registration / Referral | B57: Intake and registration of a new patient, or referral of a patient between providers. | C57: Social Security Number (SSN) | D57: Social Security Number (SSN) | E57: Government Identifier | F57: PII | G57: MUST_HAVE | H57: CRITICAL | I57: Identity theft, account fraud, impersonation, and long-term privacy harm — a US SSN cannot practically be reissued. | J57: NIST SP 800-122 / HIPAA Privacy Rule (in health context) | K57: SP 800-122 §2.1 — high-impact PII example; 45 CFR 164.514(b)(2)(I) if in a health record | L57: United States | M57: https://csrc.nist.gov/pubs/sp/800/122/final | N57: REGULATION | O57: Government identifier | P57: HIGH
A58: Patient Registration / Referral | B58: Intake and registration of a new patient, or referral of a patient between providers. | C58: Medical Record Number (MRN) | D58: Medical Record Number (MRN) | E58: Direct Identifier | F58: PHI | G58: MUST_HAVE | H58: CRITICAL | I58: Directly links an individual to their entire clinical history; enables medical-identity theft and insurance fraud. | J58: HIPAA Privacy Rule | K58: 45 CFR 164.514(b)(2)(I) — Medical record numbers | L58: United States — HIPAA covered entities | M58: https://www.hhs.gov/hipaa/for-professionals/special-topics/de-identification/index.html | N58: REGULATION | O58: PHI / health information | P58: HIGH
A59: Patient Registration / Referral | B59: Intake and registration of a new patient, or referral of a patient between providers. | C59: Health Insurance Policy Number | D59: Health Insurance Policy Number | E59: Direct Identifier | F59: PHI | G59: MUST_HAVE | H59: HIGH | I59: Enables fraudulent insurance claims and unauthorized access to coverage details. | J59: HIPAA Privacy Rule | K59: 45 CFR 164.514(b)(2)(I) — Health plan beneficiary numbers | L59: United States — HIPAA covered entities | M59: https://www.hhs.gov/hipaa/for-professionals/special-topics/de-identification/index.html | N59: REGULATION | O59: PHI / health information | P59: HIGH
A60: Patient Registration / Referral | B60: Intake and registration of a new patient, or referral of a patient between providers. | C60: Treating Provider Name / NPI Number | D60: Treating Provider Name / NPI Number | E60: Direct Identifier | F60: PHI | G60: NICE_TO_HAVE | H60: MEDIUM | I60: Discloses the treating clinician; can support social engineering against the practice, lower risk to the patient directly. | J60: HIPAA Privacy Rule | K60: 45 CFR 164.514(b)(2) — related identifiers | L60: United States — HIPAA covered entities | M60: https://www.hhs.gov/hipaa/for-professionals/special-topics/de-identification/index.html | N60: REGULATION | O60: PHI / health information | P60: MEDIUM
A61: Patient Registration / Referral | B61: Intake and registration of a new patient, or referral of a patient between providers. | C61: Signature | D61: Signature | E61: Direct Identifier | F61: PII | G61: NICE_TO_HAVE | H61: MEDIUM | I61: Enables forgery of authorization for treatment or disclosure. | J61: HIPAA Privacy Rule | K61: 45 CFR 164.514(b)(2) — Safe Harbor identifier list | L61: United States — HIPAA covered entities & business associates | M61: https://www.hhs.gov/hipaa/for-professionals/special-topics/de-identification/index.html | N61: REGULATION | O61: Explicitly protected identifier | P61: MEDIUM
A62: Explanation of Benefits (EOB) / Medical Claim | B62: Submission and adjudication of a claim for reimbursement of healthcare services. Encompasses both the Explanation of Benefits (EOB) issued to a member after a claim is processed and the underlying medical/health-insurance claim submission itself. | C62: Full Name / Person Name | D62: Full Name / Person Name | E62: Direct Identifier | F62: PII | G62: MUST_HAVE | H62: CRITICAL | I62: Re-identifies an individual's health record; enables medical-identity theft and targeted harassment. | J62: HIPAA Privacy Rule | K62: 45 CFR 164.514(b)(2) — Safe Harbor identifier list | L62: United States — HIPAA covered entities & business associates | M62: https://www.hhs.gov/hipaa/for-professionals/special-topics/de-identification/index.html | N62: REGULATION | O62: Explicitly protected identifier | P62: MEDIUM
A63: Explanation of Benefits (EOB) / Medical Claim | B63: Submission and adjudication of a claim for reimbursement of healthcare services. Encompasses both the Explanation of Benefits (EOB) issued to a member after a claim is processed and the underlying medical/health-insurance claim submission itself. | C63: Date of Birth | D63: Date of Birth | E63: Direct Identifier | F63: PII | G63: MUST_HAVE | H63: HIGH | I63: HIPAA Safe Harbor identifier; strengthens patient re-identification when combined with other fields. | J63: HIPAA Privacy Rule | K63: 45 CFR 164.514(b)(2) — Safe Harbor identifier list | L63: United States — HIPAA covered entities & business associates | M63: https://www.hhs.gov/hipaa/for-professionals/special-topics/de-identification/index.html | N63: REGULATION | O63: Explicitly protected identifier | P63: MEDIUM
... A77: Summary of Benefits and Coverage (SBC) | B77: Standardized, insurer/plan-produced disclosure (required in the U.S. group/individual health insurance market) summarizing a plan's benefits, cost-sharing, and coverage examples so a consumer/employee can compare plans; frequently distributed as a template, but sometimes issued as a personalized copy addressed to a specific enrollee. | C77: Group / Policy Number | D77: Group / Policy Number | E77: Administrative Identifier | F77: PHI | G77: NICE_TO_HAVE | H77: MEDIUM | I77: Identifies the employer/plan group rather than the individual directly; useful corroborating context but weaker re-identification value on its own. | J77: HIPAA Privacy Rule | K77: 45 CFR 164.514(b)(2) — Safe Harbor identifier list | L77: United States — HIPAA covered entities & business associates | M77: https://www.hhs.gov/hipaa/for-professionals/special-topics/de-identification/index.html | N77: REGULATION | O77: PHI / health information | P77: MEDIUM
A78: Summary of Benefits and Coverage (SBC) | B78: Standardized, insurer/plan-produced disclosure (required in the U.S. group/individual health insurance market) summarizing a plan's benefits, cost-sharing, and coverage examples so a consumer/employee can compare plans; frequently distributed as a template, but sometimes issued as a personalized copy addressed to a specific enrollee. | C78: Insurer / Carrier Name | D78: Company / Employer Name | E78: Administrative/Structural Metadata | F78: Other | G78: DROP | J78: N/A | K78: N/A | L78: N/A | M78: N/A | N78: CONTEXTUAL | O78: No meaningful privacy/security basis established | P78: HIGH
A79: Summary of Benefits and Coverage (SBC) | B79: Standardized, insurer/plan-produced disclosure (required in the U.S. group/individual health insurance market) summarizing a plan's benefits, cost-sharing, and coverage examples so a consumer/employee can compare plans; frequently distributed as a template, but sometimes issued as a personalized copy addressed to a specific enrollee. | C79: Plan Name / Tier (e.g., "Gold PPO 500") | D79: Plan Name | E79: Administrative/Structural Metadata | F79: Other | G79: DROP | J79: N/A | K79: N/A | L79: N/A | M79: N/A | N79: CONTEXTUAL | O79: No meaningful privacy/security basis established | P79: HIGH
A80: Summary of Benefits and Coverage (SBC) | B80: Standardized, insurer/plan-produced disclosure (required in the U.S. group/individual health insurance market) summarizing a plan's benefits, cost-sharing, and coverage examples so a consumer/employee can compare plans; frequently distributed as a template, but sometimes issued as a personalized copy addressed to a specific enrollee. | C80: Coverage Example Scenario (fictional patient, e.g., "Peg is Having a Baby") | D80: Coverage Example Scenario | E80: Administrative/Structural Metadata | F80: Other | G80: DROP | J80: N/A | K80: N/A | L80: N/A | M80: N/A | N80: CONTEXTUAL | O80: No meaningful privacy/security basis established | P80: HIGH
A81: Summary of Benefits and Coverage (SBC) | B81: Standardized, insurer/plan-produced disclosure (required in the U.S. group/individual health insurance market) summarizing a plan's benefits, cost-sharing, and coverage examples so a consumer/employee can compare plans; frequently distributed as a template, but sometimes issued as a personalized copy addressed to a specific enrollee. | C81: Deductible / Copay / Coinsurance Amount | D81: Cost-Sharing Amount | E81: Administrative/Structural Metadata | F81: Other | G81: DROP | J81: N/A | K81: N/A | L81: N/A | M81: N/A | N81: CONTEXTUAL | O81: No meaningful privacy/security basis established | P81: MEDIUM
A82: Summary of Benefits and Coverage (SBC) | B82: Standardized, insurer/plan-produced disclosure (required in the U.S. group/individual health insurance market) summarizing a plan's benefits, cost-sharing, and coverage examples so a consumer/employee can compare plans; frequently distributed as a template, but sometimes issued as a personalized copy addressed to a specific enrollee. | C82: Premium Amount (on personalized copy) | D82: Premium Amount | E82: Financial Data | F82: PII/Financial | G82: NICE_TO_HAVE | H82: MEDIUM | I82: Reveals an individual's personal healthcare spending obligation; sensitive but lower breach impact than an account or card number. | J82: FTC Safeguards Rule | K82: 16 CFR Part 314 | L82: United States — GLBA-covered financial institutions | M82: https://www.ftc.gov/legal-library/browse/rules/safeguards-rule | N82: REGULATION | O82: Financial/payment information | P82: MEDIUM
A83: Health Insurance Policy / Benefits Document | B83: A member's individual policy, certificate of coverage, or benefits-summary document issued by a health plan describing that specific enrollee's (and dependents') coverage, identifiers, and billing arrangement — distinct from the generic, non-personalized SBC template. | C83: Policyholder / Member Full Name | D83: Full Name / Person Name | E83: Direct Identifier | F83: PHI | G83: MUST_HAVE | H83: CRITICAL | I83: Directly identifies the individual whose coverage and health-plan enrollment the document describes; medical-identity theft and targeted-fraud risk. | J83: HIPAA Privacy Rule | K83: 45 CFR 164.514(b)(2) — Safe Harbor identifier list | L83: United States — HIPAA covered entities & business associates | M83: https://www.hhs.gov/hipaa/for-professionals/special-topics/de-identification/index.html | N83: REGULATION | O83: PHI / health information | P83: HIGH
A84: Health Insurance Policy / Benefits Document | B84: A member's individual policy, certificate of coverage, or benefits-summary document issued by a health plan describing that specific enrollee's (and dependents') coverage, identifiers, and billing arrangement — distinct from the generic, non-personalized SBC template. | C84: Dependent Name(s) | D84: Full Name / Person Name | E84: Direct Identifier | F84: PHI | G84: MUST_HAVE | H84: HIGH | I84: Identifies covered family members, including minors, tied to the same health-plan record. | J84: HIPAA Privacy Rule | K84: 45 CFR 164.514(b)(2) — Safe Harbor identifier list | L84: United States — HIPAA covered entities & business associates | M84: https://www.hhs.gov/hipaa/for-professionals/special-topics/de-identification/index.html | N84: REGULATION | O84: PHI / health information | P84: MEDIUM
A85: Health Insurance Policy / Benefits Document | B85: A member's individual policy, certificate of coverage, or benefits-summary document issued by a health plan describing that specific enrollee's (and dependents') coverage, identifiers, and billing arrangement — distinct from the generic, non-personalized SBC template. | C85: Date of Birth (policyholder/dependents) | D85: Date of Birth | E85: Direct Identifier | F85: PHI | G85: MUST_HAVE | H85: HIGH | I85: Combined with name, enables identity verification bypass and medical-identity theft. | J85: HIPAA Privacy Rule | K85: 45 CFR 164.514(b)(2) — Safe Harbor identifier list | L85: United States — HIPAA covered entities & business associates | M85: https://www.hhs.gov/hipaa/for-professionals/special-topics/de-identification/index.html | N85: REGULATION | O85: PHI / health information | P85: HIGH
A86: Health Insurance Policy / Benefits Document | B86: A member's individual policy, certificate of coverage, or benefits-summary document issued by a health plan describing that specific enrollee's (and dependents') coverage, identifiers, and billing arrangement — distinct from the generic, non-personalized SBC template. | C86: Member / Subscriber ID | D86: Health Plan Beneficiary/Member Number | E86: Direct Identifier | F86: PHI | G86: MUST_HAVE | H86: HIGH | I86: Uniquely identifies the enrollee within the plan; enables unauthorized benefits access and medical-identity theft. | J86: HIPAA Privacy Rule | K86: 45 CFR 164.514(b)(2) — Safe Harbor identifier list | L86: United States — HIPAA covered entities & business associates | M86: https://www.hhs.gov/hipaa/for-professionals/special-topics/de-identification/index.html | N86: REGULATION | O86: PHI / health information | P86: HIGH
A87: Health Insurance Policy / Benefits Document | B87: A member's individual policy, certificate of coverage, or benefits-summary document issued by a health plan describing that specific enrollee's (and dependents') coverage, identifiers, and billing arrangement — distinct from the generic, non-personalized SBC template. | C87: Social Security Number (legacy subscriber ID) | D87: Social Security Number (SSN) | E87: Government Identifier | F87: PII | G87: MUST_HAVE | H87: CRITICAL | I87: Identity theft, fraud, and impersonation; SSN is a high-value, standalone-exploitable identifier. | J87: NIST SP 800-122 / HIPAA Privacy Rule (in health context) | K87: SP 800-122 §2.1 — SSN as high-impact PII; 45 CFR 164.514(b)(2) when tied to a health record | L87: United States | M87: https://csrc.nist.gov/pubs/sp/800/122/final | N87: REGULATION | O87: Government identifier | P87: MEDIUM
A88: Health Insurance Policy / Benefits Document | B88: A member's individual policy, certificate of coverage, or benefits-summary document issued by a health plan describing that specific enrollee's (and dependents') coverage, identifiers, and billing arrangement — distinct from the generic, non-personalized SBC template. | C88: Mailing Address | D88: Street / Mailing Address | E88: Direct Identifier | F88: PHI | G88: MUST_HAVE | H88: HIGH | I88: Enables physical-world location of the individual; HIPAA Safe Harbor geographic identifier. | J88: HIPAA Privacy Rule | K88: 45 CFR 164.514(b)(2) — Safe Harbor identifier list | L88: United States — HIPAA covered entities & business associates | M88: https://www.hhs.gov/hipaa/for-professionals/special-topics/de-identification/index.html | N88: REGULATION | O88: PHI / health information | P88: HIGH
A89: Health Insurance Policy / Benefits Document | B89: A member's individual policy, certificate of coverage, or benefits-summary document issued by a health plan describing that specific enrollee's (and dependents') coverage, identifiers, and billing arrangement — distinct from the generic, non-personalized SBC template. | C89: Phone Number | D89: Phone Number | E89: Direct Identifier | F89: PHI | G89: MUST_HAVE | H89: MEDIUM | I89: Enables social engineering, phishing, and unwanted contact tied to a known health-plan enrollee. | J89: HIPAA Privacy Rule | K89: 45 CFR 164.514(b)(2) — Safe Harbor identifier list | L89: United States — HIPAA covered entities & business associates | M89: https://www.hhs.gov/hipaa/for-professionals/special-topics/de-identification/index.html | N89: REGULATION | O89: PHI / health information | P89: HIGH
A90: Health Insurance Policy / Benefits Document | B90: A member's individual policy, certificate of coverage, or benefits-summary document issued by a health plan describing that specific enrollee's (and dependents') coverage, identifiers, and billing arrangement — distinct from the generic, non-personalized SBC template. | C90: Bank Account / Auto-Pay Payment Info | D90: Bank Account Number | E90: Financial Account Data | F90: Financial | G90: MUST_HAVE | H90: HIGH | I90: Direct financial-fraud and account-takeover risk if premium auto-pay banking details are exposed. | J90: FTC Safeguards Rule | K90: 16 CFR Part 314 | L90: United States — GLBA-covered financial institutions | M90: https://www.ftc.gov/legal-library/browse/rules/safeguards-rule | N90: REGULATION | O90: Financial/payment information | P90: HIGH
A91: Health Insurance Policy / Benefits Document | B91: A member's individual policy, certificate of coverage, or benefits-summary document issued by a health plan describing that specific enrollee's (and dependents') coverage, identifiers, and billing arrangement — distinct from the generic, non-personalized SBC template. | C91: Premium Amount / Billing Statement Detail | D91: Premium Amount | E91: Financial Data | F91: PII/Financial | G91: NICE_TO_HAVE | H91: MEDIUM | I91: Reveals personal financial obligation tied to an identifiable enrollee; lower breach impact than an account number. | J91: FTC Safeguards Rule | K91: 16 CFR Part 314 | L91: United States — GLBA-covered financial institutions | M91: https://www.ftc.gov/legal-library/browse/rules/safeguards-rule | N91: REGULATION | O91: Financial/payment information | P91: MEDIUM
A92: Health Insurance Policy / Benefits Document | B92: A member's individual policy, certificate of coverage, or benefits-summary document issued by a health plan describing that specific enrollee's (and dependents') coverage, identifiers, and billing arrangement — distinct from the generic, non-personalized SBC template. | C92: Coverage Effective / Termination Date | D92: Coverage Date | E92: Administrative Identifier | F92: PHI | G92: NICE_TO_HAVE | H92: MEDIUM | I92: Reveals enrollment timeline for a specific individual; lower standalone re-identification value than a direct identifier. | J92: HIPAA Privacy Rule | K92: 45 CFR 164.514(b)(2) — Safe Harbor identifier list | L92: United States — HIPAA covered entities & business associates | M92: https://www.hhs.gov/hipaa/for-professionals/special-topics/de-identification/index.html | N92: REGULATION | O92: PHI / health information | P92: MEDIUM
A93: Health Insurance Policy / Benefits Document | B93: A member's individual policy, certificate of coverage, or benefits-summary document issued by a health plan describing that specific enrollee's (and dependents') coverage, identifiers, and billing arrangement — distinct from the generic, non-personalized SBC template. | C93: Plan Benefit Schedule / Coverage Tier Description | D93: Plan Name | E93: Administrative/Structural Metadata | F93: Other | G93: DROP | J93: N/A | K93: N/A | L93: N/A | M93: N/A | N93: CONTEXTUAL | O93: No meaningful privacy/security basis established | P93: MEDIUM
A94: Health Insurance Policy / Benefits Document | B94: A member's individual policy, certificate of coverage, or benefits-summary document issued by a health plan describing that specific enrollee's (and dependents') coverage, identifiers, and billing arrangement — distinct from the generic, non-personalized SBC template. | C94: Insurer Name / Logo / Customer Service Number | D94: Company / Employer Name | E94: Administrative/Structural Metadata | F94: Other | G94: DROP | J94: N/A | K94: N/A | L94: N/A | M94: N/A | N94: CONTEXTUAL | O94: No meaningful privacy/security basis established | P94: HIGH
A95: Medical Appointment / Appointment Reminder | B95: Scheduling confirmation or reminder (letter, SMS-derived transcript, email, or portal notice) sent to a patient ahead of a healthcare visit, identifying the patient, the visit, and often the clinic/department. | C95: Patient Full Name | D95: Full Name / Person Name | E95: Direct Identifier | F95: PHI | G95: MUST_HAVE | H95: CRITICAL | I95: Re-identifies the individual as a patient of a specific provider; medical-identity theft. | J95: HIPAA Privacy Rule | K95: 45 CFR 164.514(b)(2) — Safe Harbor identifier list | L95: United States — HIPAA covered entities & business associates | M95: https://www.hhs.gov/hipaa/for-professionals/special-topics/de-identification/index.html | N95: REGULATION | O95: PHI / health information | P95: HIGH
A96: Medical Appointment / Appointment Reminder | B96: Scheduling confirmation or reminder (letter, SMS-derived transcript, email, or portal notice) sent to a patient ahead of a healthcare visit, identifying the patient, the visit, and often the clinic/department. | C96: Medical Record Number (MRN) | D96: Medical Record Number (MRN) | E96: Direct Identifier | F96: PHI | G96: MUST_HAVE | H96: CRITICAL | I96: Uniquely links the individual to their complete clinical record across the health system. | J96: HIPAA Privacy Rule | K96: 45 CFR 164.514(b)(2) — Safe Harbor identifier list | L96: United States — HIPAA covered entities & business associates | M96: https://www.hhs.gov/hipaa/for-professionals/special-topics/de-identification/index.html | N96: REGULATION | O96: PHI / health information | P96: HIGH
A97: Medical Appointment / Appointment Reminder | B97: Scheduling confirmation or reminder (letter, SMS-derived transcript, email, or portal notice) sent to a patient ahead of a healthcare visit, identifying the patient, the visit, and often the clinic/department. | C97: Reason for Visit / Chief Complaint | D97: Diagnosis / Medical Condition | E97: Health/Clinical Data | F97: PHI | G97: MUST_HAVE | H97: CRITICAL | I97: Directly discloses a sensitive health condition or reason for care; discrimination and privacy harm if exposed. | J97: HIPAA Privacy Rule | K97: 45 CFR 164.514(b)(2) — Safe Harbor identifier list; HIPAA "any health information" standard | L97: United States — HIPAA covered entities & business associates | M97: https://www.hhs.gov/hipaa/for-professionals/special-topics/de-identification/index.html | N97: REGULATION | O97: PHI / health information | P97: MEDIUM
A98: Medical Appointment / Appointment Reminder | B98: Scheduling confirmation or reminder (letter, SMS-derived transcript, email, or portal notice) sent to a patient ahead of a healthcare visit, identifying the patient, the visit, and often the clinic/department. | C98: Clinic/Department Name (condition-revealing, e.g., Oncology, Behavioral Health, HIV Clinic) | D98: Department / Specialty Name | E98: Health/Clinical Data | F98: PHI | G98: MUST_HAVE | H98: HIGH | I98: A specialty/department name can itself disclose a sensitive health category (cancer, mental health, reproductive health, infectious disease) even without an explicit diagnosis being stated. | J98: HIPAA Privacy Rule | K98: 45 CFR 164.514(b)(2) — Safe Harbor identifier list; HIPAA "any health information" standard | L98: United States — HIPAA covered entities & business associates | M98: https://www.hhs.gov/hipaa/for-professionals/special-topics/de-identification/index.html | N98: REGULATION | O98: PHI / health information | P98: MEDIUM
A99: Medical Appointment / Appointment Reminder | B99: Scheduling confirmation or reminder (letter, SMS-derived transcript, email, or portal notice) sent to a patient ahead of a healthcare visit, identifying the patient, the visit, and often the clinic/department. | C99: Provider Name | D99: Treating Provider Name / NPI Number | E99: Direct Identifier | F99: PHI | G99: NICE_TO_HAVE | H99: MEDIUM | I99: Corroborating identifier that, combined with a specialty, can reinforce inference of a sensitive condition; lower standalone risk than the patient's own identity. | J99: HIPAA Privacy Rule | K99: 45 CFR 164.514(b)(2) — Safe Harbor identifier list | L99: United States — HIPAA covered entities & business associates | M99: https://www.hhs.gov/hipaa/for-professionals/special-topics/de-identification/index.html | N99: REGULATION | O99: PHI / health information | P99: MEDIUM
A100: Medical Appointment / Appointment Reminder | B100: Scheduling confirmation or reminder (letter, SMS-derived transcript, email, or portal notice) sent to a patient ahead of a healthcare visit, identifying the patient, the visit, and often the clinic/department. | C100: Patient Phone Number | D100: Phone Number | E100: Direct Identifier | F100: PHI | G100: MUST_HAVE | H100: MEDIUM | I100: Enables social engineering/phishing and unwanted contact; also carries independent regulatory exposure for automated reminder calls/texts. | J100: HIPAA Privacy Rule | K100: 45 CFR 164.514(b)(2) — Safe Harbor identifier list | L100: United States — HIPAA covered entities & business associates | M100: https://www.hhs.gov/hipaa/for-professionals/special-topics/de-identification/index.html | N100: REGULATION | O100: PHI / health information | P100: HIGH
A101: Medical Appointment / Appointment Reminder | B101: Scheduling confirmation or reminder (letter, SMS-derived transcript, email, or portal notice) sent to a patient ahead of a healthcare visit, identifying the patient, the visit, and often the clinic/department. | C101: Patient Email Address | D101: Email Address | E101: Direct Identifier | F101: PHI | G101: NICE_TO_HAVE | H101: MEDIUM | I101: Enables phishing and account-targeting; moderate standalone breach impact. | J101: HIPAA Privacy Rule | K101: 45 CFR 164.514(b)(2) — Safe Harbor identifier list | L101: United States — HIPAA covered entities & business associates | M101: https://www.hhs.gov/hipaa/for-professionals/special-topics/de-identification/index.html | N101: REGULATION | O101: PHI / health information | P101: HIGH
A102: Medical Appointment / Appointment Reminder | B102: Scheduling confirmation or reminder (letter, SMS-derived transcript, email, or portal notice) sent to a patient ahead of a healthcare visit, identifying the patient, the visit, and often the clinic/department. | C102: Insurance / Member ID (when included on reminder) | D102: Health Plan Beneficiary/Member Number | E102: Direct Identifier | F102: PHI | G102: NICE_TO_HAVE | H102: MEDIUM | I102: Enables unauthorized benefits inquiries if exposed; not always present on scheduling reminders. | J102: HIPAA Privacy Rule | K102: 45 CFR 164.514(b)(2) — Safe Harbor identifier list | L102: United States — HIPAA covered entities & business associates | M102: https://www.hhs.gov/hipaa/for-professionals/special-topics/de-identification/index.html | N102: REGULATION | O102: PHI / health information | P102: MEDIUM
A103: Medical Appointment / Appointment Reminder | B103: Scheduling confirmation or reminder (letter, SMS-derived transcript, email, or portal notice) sent to a patient ahead of a healthcare visit, identifying the patient, the visit, and often the clinic/department. | C103: Appointment Confirmation / Booking Reference Number | D103: Booking Reference Number | E103: Administrative/Structural Metadata | F103: Other | G103: DROP | J103: N/A | K103: N/A | L103: N/A | M103: N/A | N103: CONTEXTUAL | O103: Dependency-specific field | P103: MEDIUM
A104: Medical Appointment / Appointment Reminder | B104: Scheduling confirmation or reminder (letter, SMS-derived transcript, email, or portal notice) sent to a patient ahead of a healthcare visit, identifying the patient, the visit, and often the clinic/department. | C104: Clinic General Address / Directions | D104: Facility Address | E104: Administrative/Structural Metadata | F104: Other | G104: DROP | J104: N/A | K104: N/A | L104: N/A | M104: N/A | N104: CONTEXTUAL | O104: No meaningful privacy/security basis established | P104: MEDIUM
A105: Healthcare Data Breach Notification Letter | B105: Legally-mandated notification (HIPAA Breach Notification Rule / applicable state law) sent to an affected individual after unauthorized access, use, or disclosure of their PHI, describing what happened, what data was involved, and what remediation is offered. Must be evaluated as a healthcare/PHI document, not treated under generic-letter DROP defaults, because it typically restates the individual's own compromised PHI/PII inline. | C105: Affected Individual Full Name | D105: Full Name / Person Name | E105: Direct Identifier | F105: PHI | G105: MUST_HAVE | H105: CRITICAL | I105: Directly identifies the breach victim; combined with the described breached data, enables medical-identity theft and targeted fraud against a known-vulnerable individual. | J105: HIPAA Privacy Rule | K105: 45 CFR 164.514(b)(2) — Safe Harbor identifier list | L105: United States — HIPAA covered entities & business associates | M105: https://www.hhs.gov/hipaa/for-professionals/special-topics/de-identification/index.html | N105: REGULATION | O105: PHI / health information | P105: HIGH
A106: Healthcare Data Breach Notification Letter | B106: Legally-mandated notification (HIPAA Breach Notification Rule / applicable state law) sent to an affected individual after unauthorized access, use, or disclosure of their PHI, describing what happened, what data was involved, and what remediation is offered. Must be evaluated as a healthcare/PHI document, not treated under generic-letter DROP defaults, because it typically restates the individual's own compromised PHI/PII inline. | C106: Description of Compromised PHI/PII Elements (e.g., "your name, SSN, and diagnosis were involved") | D106: Breached Data Element Description | E106: Health/Clinical Data | F106: PHI | G106: MUST_HAVE | H106: CRITICAL | I106: Functions as an inline inventory of exactly which sensitive elements about this individual were exposed; re-exposing this text is itself a secondary disclosure of the same sensitive facts. | J106: HIPAA Privacy Rule | K106: 45 CFR 164.514(b)(2) — Safe Harbor identifier list (see Notes on breach-notification-content citation) | L106: United States — HIPAA covered entities & business associates | M106: https://www.hhs.gov/hipaa/for-professionals/special-topics/de-identification/index.html | N106: REGULATION | O106: PHI / health information | P106: MEDIUM
A107: Healthcare Data Breach Notification Letter | B107: Legally-mandated notification (HIPAA Breach Notification Rule / applicable state law) sent to an affected individual after unauthorized access, use, or disclosure of their PHI, describing what happened, what data was involved, and what remediation is offered. Must be evaluated as a healthcare/PHI document, not treated under generic-letter DROP defaults, because it typically restates the individual's own compromised PHI/PII inline. | C107: Recipient Mailing Address | D107: Street / Mailing Address | E107: Direct Identifier | F107: PHI | G107: MUST_HAVE | H107: HIGH | I107: Enables physical-world location of a known breach victim. | J107: HIPAA Privacy Rule | K107: 45 CFR 164.514(b)(2) — Safe Harbor identifier list | L107: United States — HIPAA covered entities & business associates | M107: https://www.hhs.gov/hipaa/for-professionals/special-topics/de-identification/index.html | N107: REGULATION | O107: PHI / health information | P107: HIGH
A108: Healthcare Data Breach Notification Letter | B108: Legally-mandated notification (HIPAA Breach Notification Rule / applicable state law) sent to an affected individual after unauthorized access, use, or disclosure of their PHI, describing what happened, what data was involved, and what remediation is offered. Must be evaluated as a healthcare/PHI document, not treated under generic-letter DROP defaults, because it typically restates the individual's own compromised PHI/PII inline. | C108: Medical Record Number (MRN) / Patient Account Number | D108: Medical Record Number (MRN) | E108: Direct Identifier | F108: PHI | G108: MUST_HAVE | H108: CRITICAL | I108: Uniquely links the individual to their full clinical record; frequently cited in the letter as one of the breached elements or as the letter's own identity-verification reference. | J108: HIPAA Privacy Rule | K108: 45 CFR 164.514(b)(2) — Safe Harbor identifier list | L108: United States — HIPAA covered entities & business associates | M108: https://www.hhs.gov/hipaa/for-professionals/special-topics/de-identification/index.html | N108: REGULATION | O108: PHI / health information | P108: HIGH
A109: Healthcare Data Breach Notification Letter | B109: Legally-mandated notification (HIPAA Breach Notification Rule / applicable state law) sent to an affected individual after unauthorized access, use, or disclosure of their PHI, describing what happened, what data was involved, and what remediation is offered. Must be evaluated as a healthcare/PHI document, not treated under generic-letter DROP defaults, because it typically restates the individual's own compromised PHI/PII inline. | C109: Social Security Number (partial/full, when cited as breached) | D109: Social Security Number (SSN) | E109: Government Identifier | F109: PII | G109: MUST_HAVE | H109: CRITICAL | I109: Identity theft; impersonation; fraud. | J109: NIST SP 800-122 / HIPAA Privacy Rule (in health context) | K109: SP 800-122 §2.1 — SSN as high-impact PII; 45 CFR 164.514(b)(2) when tied to a health record | L109: United States | M109: https://csrc.nist.gov/pubs/sp/800/122/final | N109: REGULATION | O109: Government identifier | P109: HIGH
A110: Healthcare Data Breach Notification Letter | B110: Legally-mandated notification (HIPAA Breach Notification Rule / applicable state law) sent to an affected individual after unauthorized access, use, or disclosure of their PHI, describing what happened, what data was involved, and what remediation is offered. Must be evaluated as a healthcare/PHI document, not treated under generic-letter DROP defaults, because it typically restates the individual's own compromised PHI/PII inline. | C110: Health Plan / Member ID (when cited as breached) | D110: Health Plan Beneficiary/Member Number | E110: Direct Identifier | F110: PHI | G110: MUST_HAVE | H110: HIGH | I110: Enables unauthorized benefits access; part of the inline breach-content description. | J110: HIPAA Privacy Rule | K110: 45 CFR 164.514(b)(2) — Safe Harbor identifier list | L110: United States — HIPAA covered entities & business associates | M110: https://www.hhs.gov/hipaa/for-professionals/special-topics/de-identification/index.html | N110: REGULATION | O110: PHI / health information | P110: MEDIUM
A111: Healthcare Data Breach Notification Letter | B111: Legally-mandated notification (HIPAA Breach Notification Rule / applicable state law) sent to an affected individual after unauthorized access, use, or disclosure of their PHI, describing what happened, what data was involved, and what remediation is offered. Must be evaluated as a healthcare/PHI document, not treated under generic-letter DROP defaults, because it typically restates the individual's own compromised PHI/PII inline. | C111: Identity-Protection / Credit-Monitoring Enrollment Code (unique per-recipient code) | D111: Enrollment/Activation Code | E111: Security Credential | F111: Credential | G111: MUST_HAVE | H111: HIGH | I111: A unique code tied to one specific recipient that grants enrollment in a remediation service; exposure enables an attacker to claim the victim's free credit-monitoring benefit or pivot into further identity fraud. | J111: No specific statutory citation in the supplied source set | K111: N/A — risk-based classification, not a specific regulatory requirement | L111: United States | M111: N/A | N111: SECURITY_RISK | O111: Sensitive authentication data | P111: MEDIUM
A112: Healthcare Data Breach Notification Letter | B112: Legally-mandated notification (HIPAA Breach Notification Rule / applicable state law) sent to an affected individual after unauthorized access, use, or disclosure of their PHI, describing what happened, what data was involved, and what remediation is offered. Must be evaluated as a healthcare/PHI document, not treated under generic-letter DROP defaults, because it typically restates the individual's own compromised PHI/PII inline. | C112: Description of Breach Incident (date discovered, general cause) | D112: Breach Incident Description | E112: Administrative/Structural Metadata | F112: Other | G112: NICE_TO_HAVE | H112: LOW | I112: Organizational/event-level information; useful context but does not by itself identify the individual or disclose their personal health information. | J112: HIPAA Privacy Rule | K112: 45 CFR 164.514(b)(2) — Safe Harbor identifier list (see Notes on breach-notification-content citation) | L112: United States — HIPAA covered entities & business associates | M112: https://www.hhs.gov/hipaa/for-professionals/special-topics/de-identification/index.html | N112: REGULATION | O112: Administrative/structural metadata (organizational event detail, mandated content but not personal to the recipient) | P112: LOW
A113: Healthcare Data Breach Notification Letter | B113: Legally-mandated notification (HIPAA Breach Notification Rule / applicable state law) sent to an affected individual after unauthorized access, use, or disclosure of their PHI, describing what happened, what data was involved, and what remediation is offered. Must be evaluated as a healthcare/PHI document, not treated under generic-letter DROP defaults, because it typically restates the individual's own compromised PHI/PII inline. | C113: Breach Response Toll-Free Number / Organization Contact Info | D113: Organization Contact Info | E113: Administrative/Structural Metadata | F113: Other | G113: DROP | J113: N/A | K113: N/A | L113: N/A | M113: N/A | N113: CONTEXTUAL | O113: No meaningful privacy/security basis established | P113: HIGH
A114: Healthcare Data Breach Notification Letter | B114: Legally-mandated notification (HIPAA Breach Notification Rule / applicable state law) sent to an affected individual after unauthorized access, use, or disclosure of their PHI, describing what happened, what data was involved, and what remediation is offered. Must be evaluated as a healthcare/PHI document, not treated under generic-letter DROP defaults, because it typically restates the individual's own compromised PHI/PII inline. | C114: Covered Entity / Organization Name & Letterhead | D114: Company / Employer Name | E114: Administrative/Structural Metadata | F114: Other | G114: DROP | J114: N/A | K114: N/A | L114: N/A | M114: N/A | N114: CONTEXTUAL | O114: No meaningful privacy/security basis established | P114: HIGH
A115: Healthcare Data Breach Notification Letter | B115: Legally-mandated notification (HIPAA Breach Notification Rule / applicable state law) sent to an affected individual after unauthorized access, use, or disclosure of their PHI, describing what happened, what data was involved, and what remediation is offered. Must be evaluated as a healthcare/PHI document, not treated under generic-letter DROP defaults, because it typically restates the individual's own compromised PHI/PII inline. | C115: Standard Regulatory Notice Boilerplate (state AG rights language, HHS complaint instructions) | D115: Boilerplate / Disclaimer Text | E115: Administrative/Structural Metadata | F115: Other | G115: DROP | J115: N/A | K115: N/A | L115: N/A | M115: N/A | N115: CONTEXTUAL | O115: Template/header rather than sensitive value | P115: MEDIUM
A116: Bank Statement | B116: Periodic statement of account activity issued by a bank to an accountholder. | C116: Full Name / Person Name | D116: Full Name / Person Name | E116: Direct Identifier | F116: PII | G116: MUST_HAVE | H116: HIGH | I116: Enables identity theft, account takeover, and social engineering when paired with account data. | J116: FTC Safeguards Rule (GLBA) / GDPR Art. 4 | K116: 16 CFR Part 314; GDPR Art. 4(1) — Personal Data | L116: United States — financial institutions; EU — if data subject is in EU | M116: https://www.ftc.gov/legal-library/browse/rules/safeguards-rule | N116: REGULATION | O116: Explicitly protected identifier | P116: MEDIUM
A117: Bank Statement | B117: Periodic statement of account activity issued by a bank to an accountholder. | C117: Street / Mailing Address | D117: Street / Mailing Address | E117: Direct Identifier | F117: PII | G117: MUST_HAVE | H117: MEDIUM | I117: Enables mail fraud, identity theft, and physical targeting when paired with financial data. | J117: FTC Safeguards Rule (GLBA) / GDPR Art. 4 | K117: 16 CFR Part 314; GDPR Art. 4(1) — Personal Data | L117: United States — financial institutions; EU — if data subject is in EU | M117: https://www.ftc.gov/legal-library/browse/rules/safeguards-rule | N117: REGULATION | O117: Explicitly protected identifier | P117: MEDIUM
A118: Bank Statement | B118: Periodic statement of account activity issued by a bank to an accountholder. | C118: Bank Account Number | D118: Bank Account Number | E118: Financial Account Data | F118: Financial | G118: MUST_HAVE | H118: CRITICAL | I118: Financial fraud, unauthorized transfers, and account targeting. | J118: FTC Safeguards Rule | K118: 16 CFR Part 314 — safeguarding customer financial account information | L118: United States — financial institutions; general risk basis elsewhere | M118: https://www.ftc.gov/legal-library/browse/rules/safeguards-rule | N118: REGULATION | O118: Financial/payment information | P118: HIGH
A119: Bank Statement | B119: Periodic statement of account activity issued by a bank to an accountholder. | C119: Bank Routing / Sort Code | D119: Bank Routing / Sort Code | E119: Financial Account Data | F119: Financial | G119: NICE_TO_HAVE | H119: MEDIUM | I119: Enables fraudulent ACH/wire setup when combined with an account number; low risk in isolation. | J119: FTC Safeguards Rule | K119: 16 CFR Part 314 | L119: United States — financial institutions; general risk basis elsewhere | M119: https://www.ftc.gov/legal-library/browse/rules/safeguards-rule | N119: REGULATION | O119: Financial/payment information | P119: HIGH
A120: Bank Statement | B120: Periodic statement of account activity issued by a bank to an accountholder. | C120: IBAN / SWIFT-BIC Code | D120: IBAN / SWIFT-BIC Code | E120: Financial Account Data | F120: Financial | G120: MUST_HAVE | H120: HIGH | I120: Enables unauthorized international wire transfers and account targeting. | J120: FTC Safeguards Rule / GDPR Art. 4 | K120: 16 CFR Part 314; GDPR Art. 4(1) | L120: International — IBAN countries; US — where a US institution is involved | M120: https://www.ftc.gov/legal-library/browse/rules/safeguards-rule | N120: REGULATION | O120: Financial/payment information | P120: HIGH
A121: Bank Statement | B121: Periodic statement of account activity issued by a bank to an accountholder. | C121: Transaction History / Amounts | D121: Transaction History / Amounts | E121: Financial Data | F121: Financial | G121: NICE_TO_HAVE | H121: LOW | I121: Discloses spending behavior/financial profile; privacy-relevant but not independently exploitable without account credentials. | J121: GDPR Art. 4 | K121: GDPR Art. 4(1) — Personal Data (where linked to an identifiable person) | L121: EU — where applicable; general risk basis elsewhere | M121: https://eur-lex.europa.eu/eli/reg/2016/679/art_4/par_1/oj | N121: REGULATION | O121: Financial/payment information | P121: MEDIUM
A122: Bank Statement | B122: Periodic statement of account activity issued by a bank to an accountholder. | C122: Phone Number | D122: Phone Number | E122: Direct Identifier | F122: PII | G122: MUST_HAVE | H122: MEDIUM | I122: Enables account-recovery social engineering and SIM-swap style fraud. | J122: FTC Safeguards Rule (GLBA) / GDPR Art. 4 | K122: 16 CFR Part 314; GDPR Art. 4(1) — Personal Data | L122: United States — financial institutions; EU — if data subject is in EU | M122: https://www.ftc.gov/legal-library/browse/rules/safeguards-rule | N122: REGULATION | O122: Explicitly protected identifier | P122: MEDIUM
A123: Bank Statement | B123: Periodic statement of account activity issued by a bank to an accountholder. | C123: Social Security Number (SSN) | D123: Social Security Number (SSN) | E123: Government Identifier | F123: PII | G123: MUST_HAVE | H123: CRITICAL | I123: Identity theft, account fraud, impersonation, and long-term privacy harm — a US SSN cannot practically be reissued. | J123: NIST SP 800-122 / HIPAA Privacy Rule (in health context) | K123: SP 800-122 §2.1 — high-impact PII example; 45 CFR 164.514(b)(2)(I) if in a health record | L123: United States | M123: https://csrc.nist.gov/pubs/sp/800/122/final | N123: REGULATION | O123: Government identifier | P123: HIGH
A124: Credit Card Statement | B124: Periodic statement of card transactions and balance issued to a cardholder. | C124: Full Name / Person Name | D124: Full Name / Person Name | E124: Direct Identifier | F124: PII | G124: MUST_HAVE | H124: HIGH | I124: Enables identity theft, account takeover, and social engineering when paired with account data. | J124: FTC Safeguards Rule (GLBA) / GDPR Art. 4 | K124: 16 CFR Part 314; GDPR Art. 4(1) — Personal Data | L124: United States — financial institutions; EU — if data subject is in EU | M124: https://www.ftc.gov/legal-library/browse/rules/safeguards-rule | N124: REGULATION | O124: Explicitly protected identifier | P124: MEDIUM
A125: Credit Card Statement | B125: Periodic statement of card transactions and balance issued to a cardholder. | C125: Street / Mailing Address | D125: Street / Mailing Address | E125: Direct Identifier | F125: PII | G125: MUST_HAVE | H125: MEDIUM | I125: Enables mail fraud, identity theft, and physical targeting when paired with financial data. | J125: FTC Safeguards Rule (GLBA) / GDPR Art. 4 | K125: 16 CFR Part 314; GDPR Art. 4(1) — Personal Data | L125: United States — financial institutions; EU — if data subject is in EU | M125: https://www.ftc.gov/legal-library/browse/rules/safeguards-rule | N125: REGULATION | O125: Explicitly protected identifier | P125: MEDIUM
A126: Credit Card Statement | B126: Periodic statement of card transactions and balance issued to a cardholder. | C126: Payment Card Number (PAN) | D126: Payment Card Number (PAN) | E126: Payment Card — Cardholder Data | F126: Payment | G126: MUST_HAVE | H126: CRITICAL | I126: Direct payment fraud and unauthorized transactions. | J126: PCI DSS | K126: PCI DSS — Cardholder Data definition | L126: Global — any entity storing/processing/transmitting payment cards | M126: https://www.pcisecuritystandards.org/faqs/1335/ | N126: STANDARD | O126: Financial/payment information | P126: HIGH
A127: Credit Card Statement | B127: Periodic statement of card transactions and balance issued to a cardholder. | C127: Card Expiration Date | D127: Card Expiration Date | E127: Payment Card — Cardholder Data | F127: Payment | G127: NICE_TO_HAVE | H127: MEDIUM | I127: Low value alone; increases fraud risk only when paired with the PAN and cardholder name. | J127: PCI DSS | K127: PCI DSS — Cardholder Data definition (permitted to store) | L127: Global | M127: https://www.pcisecuritystandards.org/faqs/1335/ | N127: STANDARD | O127: Financial/payment information | P127: HIGH
... A136: Payment Document / Receipt | B136: Record of a completed payment transaction between a payer and a merchant/payee. | C136: Transaction History / Amounts | D136: Transaction History / Amounts | E136: Financial Data | F136: Financial | G136: NICE_TO_HAVE | H136: LOW | I136: Discloses spending behavior/financial profile; privacy-relevant but not independently exploitable without account credentials. | J136: GDPR Art. 4 | K136: GDPR Art. 4(1) — Personal Data (where linked to an identifiable person) | L136: EU — where applicable; general risk basis elsewhere | M136: https://eur-lex.europa.eu/eli/reg/2016/679/art_4/par_1/oj | N136: REGULATION | O136: Financial/payment information | P136: MEDIUM
A137: Payment Document / Receipt | B137: Record of a completed payment transaction between a payer and a merchant/payee. | C137: Merchant / Vendor Name | D137: Merchant / Vendor Name | E137: Administrative/Structural Metadata | F137: Other | G137: DROP | I137: None on its own — identifies a business, not the data subject; standard commercial information. | J137: N/A | K137: N/A | L137: N/A | N137: CONTEXTUAL | O137: No meaningful privacy/security basis established | P137: HIGH
A138: Payment Document / Receipt | B138: Record of a completed payment transaction between a payer and a merchant/payee. | C138: Invoice Number | D138: Invoice Number | E138: Administrative/Structural Metadata | F138: Other | G138: DROP | I138: None — an internal business/accounting reference, not linked to an individual's protected data. | J138: N/A | K138: N/A | L138: N/A | N138: CONTEXTUAL | O138: Dependency-specific field | P138: HIGH
A139: Payment Document / Receipt | B139: Record of a completed payment transaction between a payer and a merchant/payee. | C139: Line-item Product/Service Description | D139: Line-item Product/Service Description | E139: Administrative/Structural Metadata | F139: Other | G139: DROP | I139: None — describes a purchased product/service, not the individual. | J139: N/A | K139: N/A | L139: N/A | N139: CONTEXTUAL | O139: No meaningful privacy/security basis established | P139: HIGH
A140: Payment Document / Receipt | B140: Record of a completed payment transaction between a payer and a merchant/payee. | C140: Street / Mailing Address | D140: Street / Mailing Address | E140: Direct Identifier | F140: PII | G140: MUST_HAVE | H140: MEDIUM | I140: Enables mail fraud, identity theft, and physical targeting when paired with financial data. | J140: FTC Safeguards Rule (GLBA) / GDPR Art. 4 | K140: 16 CFR Part 314; GDPR Art. 4(1) — Personal Data | L140: United States — financial institutions; EU — if data subject is in EU | M140: https://www.ftc.gov/legal-library/browse/rules/safeguards-rule | N140: REGULATION | O140: Explicitly protected identifier | P140: MEDIUM
A141: Invoice / Purchase Order | B141: Commercial billing document requesting or confirming payment for goods/services. | C141: Full Name / Person Name | D141: Full Name / Person Name | E141: Direct Identifier | F141: PII | G141: MUST_HAVE | H141: HIGH | I141: Enables identity theft, account takeover, and social engineering when paired with account data. | J141: FTC Safeguards Rule (GLBA) / GDPR Art. 4 | K141: 16 CFR Part 314; GDPR Art. 4(1) — Personal Data | L141: United States — financial institutions; EU — if data subject is in EU | M141: https://www.ftc.gov/legal-library/browse/rules/safeguards-rule | N141: REGULATION | O141: Explicitly protected identifier | P141: MEDIUM
A142: Invoice / Purchase Order | B142: Commercial billing document requesting or confirming payment for goods/services. | C142: Street / Mailing Address | D142: Street / Mailing Address | E142: Direct Identifier | F142: PII | G142: MUST_HAVE | H142: MEDIUM | I142: Enables mail fraud, identity theft, and physical targeting when paired with financial data. | J142: FTC Safeguards Rule (GLBA) / GDPR Art. 4 | K142: 16 CFR Part 314; GDPR Art. 4(1) — Personal Data | L142: United States — financial institutions; EU — if data subject is in EU | M142: https://www.ftc.gov/legal-library/browse/rules/safeguards-rule | N142: REGULATION | O142: Explicitly protected identifier | P142: MEDIUM
A143: Invoice / Purchase Order | B143: Commercial billing document requesting or confirming payment for goods/services. | C143: Company / Employer Name | D143: Company / Employer Name | E143: Administrative/Structural Metadata | F143: Other | G143: DROP | I143: None on its own — organizational data; only becomes privacy-relevant combined with an individual identifier already captured separately. | J143: N/A | K143: N/A | L143: N/A | N143: CONTEXTUAL | O143: No meaningful privacy/security basis established | P143: MEDIUM
...

Sheet Document_Summary
A1: Document Type | B1: Business Workflow | C1: Primary Regulations | D1: Relevant Policies | E1: Must-Have Entity Count | F1: Nice-to-Have Entity Count | G1: Drop Entity Count | H1: Critical-Risk Entity Count | I1: High-Risk Entity Count | J1: Main Threats | K1: Notes
A2: Medical Record / Clinical Note | B2: Ongoing clinical documentation of a patient's encounters, diagnoses, and treatment to support continuity of care. | C2: HIPAA Privacy Rule | D2: Company policy evidence not supplied. | E2: =COUNTIFS(Master_Entity_Policy!$A$2:$A$287,$A2,Master_Entity_Policy!$G$2:$G$287,"MUST_HAVE") -> 9 | F2: =COUNTIFS(Master_Entity_Policy!$A$2:$A$287,$A2,Master_Entity_Policy!$G$2:$G$287,"NICE_TO_HAVE") -> 6 | G2: =COUNTIFS(Master_Entity_Policy!$A$2:$A$287,$A2,Master_Entity_Policy!$G$2:$G$287,"DROP") -> 0 | H2: =COUNTIFS(Master_Entity_Policy!$A$2:$A$287,$A2,Master_Entity_Policy!$H$2:$H$287,"CRITICAL") -> 4 | I2: =COUNTIFS(Master_Entity_Policy!$A$2:$A$287,$A2,Master_Entity_Policy!$H$2:$H$287,"HIGH") -> 3 | J2: Can reveal a sensitive condition by inference (e.g., psychiatric, HIV, oncology drugs); enables prescription fraud.; Directly links an individual to their entire clinical history; enables medical-identity theft and insurance fraud.; Discloses the treating clinician; can support social engineering against the practice, lower risk to the patient directly.; Discloses treatment history; can imply a condition (re-identification risk) and support insurance fraud.; Discrimination, stigmatization, employment/insurance harm, and medical-privacy harm if disclosed. | K2: See Master_Entity_Policy for full entity-level detail.
A3: Lab Report / Pathology Report | B3: Laboratory or pathology testing and result reporting to support diagnosis and treatment decisions. | C3: HIPAA Privacy Rule | D3: Company policy evidence not supplied. | E3: =COUNTIFS(Master_Entity_Policy!$A$2:$A$287,$A3,Master_Entity_Policy!$G$2:$G$287,"MUST_HAVE") -> 5 | F3: =COUNTIFS(Master_Entity_Policy!$A$2:$A$287,$A3,Master_Entity_Policy!$G$2:$G$287,"NICE_TO_HAVE") -> 2 | G3: =COUNTIFS(Master_Entity_Policy!$A$2:$A$287,$A3,Master_Entity_Policy!$G$2:$G$287,"DROP") -> 1 | H3: =COUNTIFS(Master_Entity_Policy!$A$2:$A$287,$A3,Master_Entity_Policy!$H$2:$H$287,"CRITICAL") -> 3 | I3: =COUNTIFS(Master_Entity_Policy!$A$2:$A$287,$A3,Master_Entity_Policy!$H$2:$H$287,"HIGH") -> 1 | J3: Directly links an individual to their entire clinical history; enables medical-identity theft and insurance fraud.; Discloses physiological/health status; moderate standalone risk, higher when linked to identity.; Discloses the treating clinician; can support social engineering against the practice, lower risk to the patient directly.; Discrimination, stigmatization, employment/insurance harm, and medical-privacy harm if disclosed.; Enables re-identification when correlated with public event data (e.g., accident reports); listed HIPAA identifier. | K3: See Master_Entity_Policy for full entity-level detail.
A4: Prescription | B4: Prescribing and dispensing of medication to a patient. | C4: HIPAA Privacy Rule | D4: Company policy evidence not supplied. | E4: =COUNTIFS(Master_Entity_Policy!$A$2:$A$287,$A4,Master_Entity_Policy!$G$2:$G$287,"MUST_HAVE") -> 6 | F4: =COUNTIFS(Master_Entity_Policy!$A$2:$A$287,$A4,Master_Entity_Policy!$G$2:$G$287,"NICE_TO_HAVE") -> 2 | G4: =COUNTIFS(Master_Entity_Policy!$A$2:$A$287,$A4,Master_Entity_Policy!$G$2:$G$287,"DROP") -> 0 | H4: =COUNTIFS(Master_Entity_Policy!$A$2:$A$287,$A4,Master_Entity_Policy!$H$2:$H$287,"CRITICAL") -> 2 | I4: =COUNTIFS(Master_Entity_Policy!$A$2:$A$287,$A4,Master_Entity_Policy!$H$2:$H$287,"HIGH") -> 4 | J4: Can reveal a sensitive condition by inference (e.g., psychiatric, HIV, oncology drugs); enables prescription fraud.; Directly links an individual to their entire clinical history; enables medical-identity theft and insurance fraud.; Discloses the treating clinician; can support social engineering against the practice, lower risk to the patient directly.; Enables forgery of authorization for treatment or disclosure.; Enables fraudulent insurance claims and unauthorized access to coverage details. | K4: See Master_Entity_Policy for full entity-level detail.
A5: Discharge Summary | B5: Summary of a patient's hospital stay, treatment, and follow-up plan at the point of discharge. | C5: HIPAA Privacy Rule | D5: Company policy evidence not supplied. | E5: =COUNTIFS(Master_Entity_Policy!$A$2:$A$287,$A5,Master_Entity_Policy!$G$2:$G$287,"MUST_HAVE") -> 7 | F5: =COUNTIFS(Master_Entity_Policy!$A$2:$A$287,$A5,Master_Entity_Policy!$G$2:$G$287,"NICE_TO_HAVE") -> 3 | G5: =COUNTIFS(Master_Entity_Policy!$A$2:$A$287,$A5,Master_Entity_Policy!$G$2:$G$287,"DROP") -> 0 | H5: =COUNTIFS(Master_Entity_Policy!$A$2:$A$287,$A5,Master_Entity_Policy!$H$2:$H$287,"CRITICAL") -> 4 | I5: =COUNTIFS(Master_Entity_Policy!$A$2:$A$287,$A5,Master_Entity_Policy!$H$2:$H$287,"HIGH") -> 2 | J5: Can reveal a sensitive condition by inference (e.g., psychiatric, HIV, oncology drugs); enables prescription fraud.; Directly links an individual to their entire clinical history; enables medical-identity theft and insurance fraud.; Discloses the treating clinician; can support social engineering against the practice, lower risk to the patient directly.; Discloses treatment history; can imply a condition (re-identification risk) and support insurance fraud.; Discrimination, stigmatization, employment/insurance harm, and medical-privacy harm if disclosed. | K5: See Master_Entity_Policy for full entity-level detail.
A6: Imaging / Radiology Report | B6: Interpretation and reporting of diagnostic imaging studies (X-ray, CT, MRI, ultrasound). | C6: HIPAA Privacy Rule | D6: Company policy evidence not supplied. | E6: =COUNTIFS(Master_Entity_Policy!$A$2:$A$287,$A6,Master_Entity_Policy!$G$2:$G$287,"MUST_HAVE") -> 5 | F6: =COUNTIFS(Master_Entity_Policy!$A$2:$A$287,$A6,Master_Entity_Policy!$G$2:$G$287,"NICE_TO_HAVE") -> 2 | G6: =COUNTIFS(Master_Entity_Policy!$A$2:$A$287,$A6,Master_Entity_Policy!$G$2:$G$287,"DROP") -> 2 | H6: =COUNTIFS(Master_Entity_Policy!$A$2:$A$287,$A6,Master_Entity_Policy!$H$2:$H$287,"CRITICAL") -> 3 | I6: =COUNTIFS(Master_Entity_Policy!$A$2:$A$287,$A6,Master_Entity_Policy!$H$2:$H$287,"HIGH") -> 1 | J6: Directly links an individual to their entire clinical history; enables medical-identity theft and insurance fraud.; Discloses the treating clinician; can support social engineering against the practice, lower risk to the patient directly.; Discrimination, stigmatization, employment/insurance harm, and medical-privacy harm if disclosed.; Enables re-identification when correlated with public event data (e.g., accident reports); listed HIPAA identifier.; HIPAA Safe Harbor identifier; strengthens patient re-identification when combined with other fields. | K6: See Master_Entity_Policy for full entity-level detail.
A7: Patient Registration / Referral | B7: Intake and registration of a new patient, or referral of a patient between providers. | C7: HIPAA Privacy Rule; NIST SP 800-122 | D7: Company policy evidence not supplied. | E7: =COUNTIFS(Master_Entity_Policy!$A$2:$A$287,$A7,Master_Entity_Policy!$G$2:$G$287,"MUST_HAVE") -> 8 | F7: =COUNTIFS(Master_Entity_Policy!$A$2:$A$287,$A7,Master_Entity_Policy!$G$2:$G$287,"NICE_TO_HAVE") -> 2 | G7: =COUNTIFS(Master_Entity_Policy!$A$2:$A$287,$A7,Master_Entity_Policy!$G$2:$G$287,"DROP") -> 0 | H7: =COUNTIFS(Master_Entity_Policy!$A$2:$A$287,$A7,Master_Entity_Policy!$H$2:$H$287,"CRITICAL") -> 3 | I7: =COUNTIFS(Master_Entity_Policy!$A$2:$A$287,$A7,Master_Entity_Policy!$H$2:$H$287,"HIGH") -> 3 | J7: Directly links an individual to their entire clinical history; enables medical-identity theft and insurance fraud.; Discloses the treating clinician; can support social engineering against the practice, lower risk to the patient directly.; Enables forgery of authorization for treatment or disclosure.; Enables fraudulent insurance claims and unauthorized access to coverage details.; HIPAA Safe Harbor identifier; a credential-adjacent identifier usable for phishing tied to health context. | K7: See Master_Entity_Policy for full entity-level detail.
A8: Explanation of Benefits (EOB) / Medical Claim | B8: Submission and adjudication of a claim for reimbursement of healthcare services. Encompasses both the Explanation of Benefits (EOB) issued to a member after a claim is processed and the underlying medical/health-insurance claim submission itself. | C8: HIPAA Privacy Rule; NIST SP 800-122 | D8: Company policy evidence not supplied. | E8: =COUNTIFS(Master_Entity_Policy!$A$2:$A$287,$A8,Master_Entity_Policy!$G$2:$G$287,"MUST_HAVE") -> 10 | F8: =COUNTIFS(Master_Entity_Policy!$A$2:$A$287,$A8,Master_Entity_Policy!$G$2:$G$287,"NICE_TO_HAVE") -> 3 | G8: =COUNTIFS(Master_Entity_Policy!$A$2:$A$287,$A8,Master_Entity_Policy!$G$2:$G$287,"DROP") -> 0 | H8: =COUNTIFS(Master_Entity_Policy!$A$2:$A$287,$A8,Master_Entity_Policy!$H$2:$H$287,"CRITICAL") -> 4 | I8: =COUNTIFS(Master_Entity_Policy!$A$2:$A$287,$A8,Master_Entity_Policy!$H$2:$H$287,"HIGH") -> 4 | J8: Directly links an individual to their entire clinical history; enables medical-identity theft and insurance fraud.; Discloses the treating clinician; can support social engineering against the practice, lower risk to the patient directly.; Discloses treatment history; can imply a condition (re-identification risk) and support insurance fraud.; Discrimination, stigmatization, employment/insurance harm, and medical-privacy harm if disclosed.; Enables fraudulent insurance claims and unauthorized access to coverage details. | K8: See Master_Entity_Policy for full entity-level detail.
A9: Summary of Benefits and Coverage (SBC) | B9: Standardized, insurer/plan-produced disclosure (required in the U.S. group/individual health insurance market) summarizing a plan's benefits, cost-sharing, and coverage examples so a consumer/employee can compare plans; frequently distributed as a template, but sometimes issued as a personalized copy addressed to a specific enrollee. | C9: FTC Safeguards Rule; HIPAA Privacy Rule | D9: Company policy evidence not supplied. | E9: =COUNTIFS(Master_Entity_Policy!$A$2:$A$287,$A9,Master_Entity_Policy!$G$2:$G$287,"MUST_HAVE") -> 1 | F9: =COUNTIFS(Master_Entity_Policy!$A$2:$A$287,$A9,Master_Entity_Policy!$G$2:$G$287,"NICE_TO_HAVE") -> 3 | G9: =COUNTIFS(Master_Entity_Policy!$A$2:$A$287,$A9,Master_Entity_Policy!$G$2:$G$287,"DROP") -> 4 | H9: =COUNTIFS(Master_Entity_Policy!$A$2:$A$287,$A9,Master_Entity_Policy!$H$2:$H$287,"CRITICAL") -> 0 | I9: =COUNTIFS(Master_Entity_Policy!$A$2:$A$287,$A9,Master_Entity_Policy!$H$2:$H$287,"HIGH") -> 1 | J9: Identifies the employer/plan group rather than the individual directly; useful corroborating context but weaker re-identification value on its own.; Links the individual to a specific health plan and, indirectly, to their health-plan enrollment status.; Reveals an individual's personal healthcare spending obligation; sensitive but lower breach impact than an account or card number.; Uniquely identifies a specific enrollee within a health plan; enables medical-identity theft and unauthorized benefits inquiries. | K9: See Master_Entity_Policy for full entity-level detail.
A10: Health Insurance Policy / Benefits Document | B10: A member's individual policy, certificate of coverage, or benefits-summary document issued by a health plan describing that specific enrollee's (and dependents') coverage, identifiers, and billing arrangement — distinct from the generic, non-personalized SBC template. | C10: FTC Safeguards Rule; HIPAA Privacy Rule; NIST SP 800-122 | D10: Company policy evidence not supplied. | E10: =COUNTIFS(Master_Entity_Policy!$A$2:$A$287,$A10,Master_Entity_Policy!$G$2:$G$287,"MUST_HAVE") -> 8 | F10: =COUNTIFS(Master_Entity_Policy!$A$2:$A$287,$A10,Master_Entity_Policy!$G$2:$G$287,"NICE_TO_HAVE") -> 2 | G10: =COUNTIFS(Master_Entity_Policy!$A$2:$A$287,$A10,Master_Entity_Policy!$G$2:$G$287,"DROP") -> 2 | H10: =COUNTIFS(Master_Entity_Policy!$A$2:$A$287,$A10,Master_Entity_Policy!$H$2:$H$287,"CRITICAL") -> 2 | I10: =COUNTIFS(Master_Entity_Policy!$A$2:$A$287,$A10,Master_Entity_Policy!$H$2:$H$287,"HIGH") -> 5 | J10: Combined with name, enables identity verification bypass and medical-identity theft.; Direct financial-fraud and account-takeover risk if premium auto-pay banking details are exposed.; Directly identifies the individual whose coverage and health-plan enrollment the document describes; medical-identity theft and targeted-fraud risk.; Enables physical-world location of the individual; HIPAA Safe Harbor geographic identifier.; Enables social engineering, phishing, and unwanted contact tied to a known health-plan enrollee. | K10: See Master_Entity_Policy for full entity-level detail.
A11: Medical Appointment / Appointment Reminder | B11: Scheduling confirmation or reminder (letter, SMS-derived transcript, email, or portal notice) sent to a patient ahead of a healthcare visit, identifying the patient, the visit, and often the clinic/department. | C11: HIPAA Privacy Rule | D11: Company policy evidence not supplied. | E11: =COUNTIFS(Master_Entity_Policy!$A$2:$A$287,$A11,Master_Entity_Policy!$G$2:$G$287,"MUST_HAVE") -> 5 | F11: =COUNTIFS(Master_Entity_Policy!$A$2:$A$287,$A11,Master_Entity_Policy!$G$2:$G$287,"NICE_TO_HAVE") -> 3 | G11: =COUNTIFS(Master_Entity_Policy!$A$2:$A$287,$A11,Master_Entity_Policy!$G$2:$G$287,"DROP") -> 2 | H11: =COUNTIFS(Master_Entity_Policy!$A$2:$A$287,$A11,Master_Entity_Policy!$H$2:$H$287,"CRITICAL") -> 3 | I11: =COUNTIFS(Master_Entity_Policy!$A$2:$A$287,$A11,Master_Entity_Policy!$H$2:$H$287,"HIGH") -> 1 | J11: A specialty/department name can itself disclose a sensitive health category (cancer, mental health, reproductive health, infectious disease) even without an explicit diagnosis being stated.; Corroborating identifier that, combined with a specialty, can reinforce inference of a sensitive condition; lower standalone risk than the patient's own identity.; Directly discloses a sensitive health condition or reason for care; discrimination and privacy harm if exposed.; Enables phishing and account-targeting; moderate standalone breach impact.; Enables social engineering/phishing and unwanted contact; also carries independent regulatory exposure for automated reminder calls/texts. | K11: See Master_Entity_Policy for full entity-level detail.
A12: Healthcare Data Breach Notification Letter | B12: Legally-mandated notification (HIPAA Breach Notification Rule / applicable state law) sent to an affected individual after unauthorized access, use, or disclosure of their PHI, describing what happened, what data was involved, and what remediation is offered. Must be evaluated as a healthcare/PHI document, not treated under generic-letter DROP defaults, because it typically restates the individual's own compromised PHI/PII inline. | C12: HIPAA Privacy Rule; NIST SP 800-122 | D12: Company policy evidence not supplied. | E12: =COUNTIFS(Master_Entity_Policy!$A$2:$A$287,$A12,Master_Entity_Policy!$G$2:$G$287,"MUST_HAVE") -> 7 | F12: =COUNTIFS(Master_Entity_Policy!$A$2:$A$287,$A12,Master_Entity_Policy!$G$2:$G$287,"NICE_TO_HAVE") -> 1 | G12: =COUNTIFS(Master_Entity_Policy!$A$2:$A$287,$A12,Master_Entity_Policy!$G$2:$G$287,"DROP") -> 3 | H12: =COUNTIFS(Master_Entity_Policy!$A$2:$A$287,$A12,Master_Entity_Policy!$H$2:$H$287,"CRITICAL") -> 4 | I12: =COUNTIFS(Master_Entity_Policy!$A$2:$A$287,$A12,Master_Entity_Policy!$H$2:$H$287,"HIGH") -> 3 | J12: A unique code tied to one specific recipient that grants enrollment in a remediation service; exposure enables an attacker to claim the victim's free credit-monitoring benefit or pivot into further identity fraud.; Directly identifies the breach victim; combined with the described breached data, enables medical-identity theft and targeted fraud against a known-vulnerable individual.; Enables physical-world location of a known breach victim.; Enables unauthorized benefits access; part of the inline breach-content description.; Functions as an inline inventory of exactly which sensitive elements about this individual were exposed; re-exposing this text is itself a secondary disclosure of the same sensitive facts. | K12: See Master_Entity_Policy for full entity-level detail.
A13: Bank Statement | B13: Periodic statement of account activity issued by a bank to an accountholder. | C13: FTC Safeguards Rule; FTC Safeguards Rule (GLBA); GDPR Art. 4; NIST SP 800-122 | D13: Company policy evidence not supplied. | E13: =COUNTIFS(Master_Entity_Policy!$A$2:$A$287,$A13,Master_Entity_Policy!$G$2:$G$287,"MUST_HAVE") -> 6 | F13: =COUNTIFS(Master_Entity_Policy!$A$2:$A$287,$A13,Master_Entity_Policy!$G$2:$G$287,"NICE_TO_HAVE") -> 2 | G13: =COUNTIFS(Master_Entity_Policy!$A$2:$A$287,$A13,Master_Entity_Policy!$G$2:$G$287,"DROP") -> 0 | H13: =COUNTIFS(Master_Entity_Policy!$A$2:$A$287,$A13,Master_Entity_Policy!$H$2:$H$287,"CRITICAL") -> 2 | I13: =COUNTIFS(Master_Entity_Policy!$A$2:$A$287,$A13,Master_Entity_Policy!$H$2:$H$287,"HIGH") -> 2 | J13: Discloses spending behavior/financial profile; privacy-relevant but not independently exploitable without account credentials.; Enables account-recovery social engineering and SIM-swap style fraud.; Enables fraudulent ACH/wire setup when combined with an account number; low risk in isolation.; Enables identity theft, account takeover, and social engineering when paired with account data.; Enables mail fraud, identity theft, and physical targeting when paired with financial data. | K13: See Master_Entity_Policy for full entity-level detail.
... A32: Email / Letter / General Form / Scanned Document | B32: General business or personal correspondence, forms, or scanned documents not otherwise classified. | C32: GDPR Art. 4 | D32: Company policy evidence not supplied. | E32: =COUNTIFS(Master_Entity_Policy!$A$2:$A$287,$A32,Master_Entity_Policy!$G$2:$G$287,"MUST_HAVE") -> 1 | F32: =COUNTIFS(Master_Entity_Policy!$A$2:$A$287,$A32,Master_Entity_Policy!$G$2:$G$287,"NICE_TO_HAVE") -> 4 | G32: =COUNTIFS(Master_Entity_Policy!$A$2:$A$287,$A32,Master_Entity_Policy!$G$2:$G$287,"DROP") -> 6 | H32: =COUNTIFS(Master_Entity_Policy!$A$2:$A$287,$A32,Master_Entity_Policy!$H$2:$H$287,"CRITICAL") -> 0 | I32: =COUNTIFS(Master_Entity_Policy!$A$2:$A$287,$A32,Master_Entity_Policy!$H$2:$H$287,"HIGH") -> 0 | J32: Basic identity exposure; risk rises sharply when combined with other identifiers.; Discloses residence; moderate risk on its own, higher when combined with a name.; Enables phishing, spam, and account-targeting.; Enables phishing, spam, and social engineering.; Low standalone risk; relevant mainly as forgery material in combination with other data. | K32: See Master_Entity_Policy for full entity-level detail.

Sheet Must_Have_Entities
A1: Document Type | B1: Entity | C1: Canonical Entity | D1: Category | E1: Risk Level | F1: Threat | G1: Regulation | H1: Policy | I1: Classification Basis | J1: Rationale | K1: Evidence URL
A2: Medical Record / Clinical Note | B2: Full Name / Person Name | C2: Full Name / Person Name | D2: Direct Identifier | E2: CRITICAL | F2: Re-identifies an individual's health record; enables medical-identity theft and targeted harassment. | G2: HIPAA Privacy Rule | H2: Company policy evidence not supplied. | I2: REGULATION | J2: Primary direct identifier under HIPAA Safe Harbor; combined with clinical data it converts de-identified content back into PHI. | K2: https://www.hhs.gov/hipaa/for-professionals/special-topics/de-identification/index.html
A3: Medical Record / Clinical Note | B3: Date of Birth | C3: Date of Birth | D3: Direct Identifier | E3: HIGH | F3: HIPAA Safe Harbor identifier; strengthens patient re-identification when combined with other fields. | G3: HIPAA Privacy Rule | H3: Company policy evidence not supplied. | I3: REGULATION | J3: Listed identifier requiring removal for de-identified data sets. | K3: https://www.hhs.gov/hipaa/for-professionals/special-topics/de-identification/index.html
A4: Medical Record / Clinical Note | B4: Medical Record Number (MRN) | C4: Medical Record Number (MRN) | D4: Direct Identifier | E4: CRITICAL | F4: Directly links an individual to their entire clinical history; enables medical-identity theft and insurance fraud. | G4: HIPAA Privacy Rule | H4: Company policy evidence not supplied. | I4: REGULATION | J4: Explicitly enumerated in the HIPAA Safe Harbor identifier list. | K4: https://www.hhs.gov/hipaa/for-professionals/special-topics/de-identification/index.html
A5: Medical Record / Clinical Note | B5: Street / Mailing Address | C5: Street / Mailing Address | D5: Direct Identifier | E5: HIGH | F5: HIPAA Safe Harbor identifier; discloses where a patient lives, raising both privacy and physical-safety risk. | G5: HIPAA Privacy Rule | H5: Company policy evidence not supplied. | I5: REGULATION | J5: Listed identifier requiring removal for de-identified data sets. | K5: https://www.hhs.gov/hipaa/for-professionals/special-topics/de-identification/index.html
A6: Medical Record / Clinical Note | B6: Phone Number | C6: Phone Number | D6: Direct Identifier | E6: MEDIUM | F6: HIPAA Safe Harbor identifier; enables phishing/social engineering against a patient. | G6: HIPAA Privacy Rule | H6: Company policy evidence not supplied. | I6: REGULATION | J6: Listed identifier requiring removal for de-identified data sets. | K6: https://www.hhs.gov/hipaa/for-professionals/special-topics/de-identification/index.html
A7: Medical Record / Clinical Note | B7: Diagnosis / Medical Condition | C7: Diagnosis / Medical Condition | D7: Health/Clinical Data | E7: CRITICAL | F7: Discrimination, stigmatization, employment/insurance harm, and medical-privacy harm if disclosed. | G7: HIPAA Privacy Rule | H7: Company policy evidence not supplied. | I7: REGULATION | J7: Core content-based PHI element; discloses the individual's health status. | K7: https://www.hhs.gov/hipaa/for-professionals/special-topics/de-identification/index.html
A8: Medical Record / Clinical Note | B8: Medication / Prescription Detail | C8: Medication / Prescription Detail | D8: Health/Clinical Data | E8: HIGH | F8: Can reveal a sensitive condition by inference (e.g., psychiatric, HIV, oncology drugs); enables prescription fraud. | G8: HIPAA Privacy Rule | H8: Company policy evidence not supplied. | I8: REGULATION | J8: Content-based PHI with meaningful re-identification and fraud risk (controlled substances especially). | K8: https://www.hhs.gov/hipaa/for-professionals/special-topics/de-identification/index.html
A9: Medical Record / Clinical Note | B9: Clinical Notes / Narrative | C9: Clinical Notes / Narrative | D9: Health/Clinical Data | E9: CRITICAL | F9: Free text frequently contains multiple PHI elements at once (identity + diagnosis + history); high aggregate breach impact. | G9: HIPAA Privacy Rule | H9: Company policy evidence not supplied. | I9: REGULATION | J9: Narrative text is the highest-density PHI surface in a medical record. | K9: https://www.hhs.gov/hipaa/for-professionals/special-topics/de-identification/index.html
A10: Medical Record / Clinical Note | B10: Admission / Discharge / Service Date | C10: Admission / Discharge / Service Date | D10: Direct Identifier | E10: MEDIUM | F10: Enables re-identification when correlated with public event data (e.g., accident reports); listed HIPAA identifier. | G10: HIPAA Privacy Rule | H10: Company policy evidence not supplied. | I10: REGULATION | J10: Explicitly listed in the HIPAA Safe Harbor identifier set (dates directly related to an individual, other than year). | K10: https://www.hhs.gov/hipaa/for-professionals/special-topics/de-identification/index.html
A11: Lab Report / Pathology Report | B11: Full Name / Person Name | C11: Full Name / Person Name | D11: Direct Identifier | E11: CRITICAL | F11: Re-identifies an individual's health record; enables medical-identity theft and targeted harassment. | G11: HIPAA Privacy Rule | H11: Company policy evidence not supplied. | I11: REGULATION | J11: Primary direct identifier under HIPAA Safe Harbor; combined with clinical data it converts de-identified content back into PHI. | K11: https://www.hhs.gov/hipaa/for-professionals/special-topics/de-identification/index.html
A12: Lab Report / Pathology Report | B12: Date of Birth | C12: Date of Birth | D12: Direct Identifier | E12: HIGH | F12: HIPAA Safe Harbor identifier; strengthens patient re-identification when combined with other fields. | G12: HIPAA Privacy Rule | H12: Company policy evidence not supplied. | I12: REGULATION | J12: Listed identifier requiring removal for de-identified data sets. | K12: https://www.hhs.gov/hipaa/for-professionals/special-topics/de-identification/index.html
... A173: Email / Letter / General Form / Scanned Document | B173: Full Name / Person Name | C173: Full Name / Person Name | D173: Direct Identifier | E173: MEDIUM | F173: Basic identity exposure; risk rises sharply when combined with other identifiers. | G173: GDPR Art. 4 / India DPDP Act, 2023 | H173: Company policy evidence not supplied. | I173: REGULATION | J173: Foundational direct identifier present in most general correspondence. | K173: https://eur-lex.europa.eu/eli/reg/2016/679/art_4/par_1/oj

Sheet Nice_To_Have_Entities
A1: Document Type | B1: Entity | C1: Canonical Entity | D1: Category | E1: Risk Level | F1: Threat | G1: Regulation | H1: Policy | I1: Classification Basis | J1: Rationale | K1: Evidence URL
A2: Medical Record / Clinical Note | B2: Procedure Code / Description | C2: Procedure Code / Description | D2: Health/Clinical Data | E2: MEDIUM | F2: Discloses treatment history; can imply a condition (re-identification risk) and support insurance fraud. | G2: HIPAA Privacy Rule | H2: Company policy evidence not supplied. | I2: REGULATION | J2: Content-based PHI; lower standalone severity than an explicit diagnosis but still identifies care received. | K2: https://www.hhs.gov/hipaa/for-professionals/special-topics/de-identification/index.html
A3: Medical Record / Clinical Note | B3: Allergy Information | C3: Allergy Information | D3: Health/Clinical Data | E3: MEDIUM | F3: Reveals health information; misuse risk lower than diagnosis but still privacy-sensitive. | G3: HIPAA Privacy Rule | H3: Company policy evidence not supplied. | I3: REGULATION | J3: Content-based PHI, secondary to primary diagnosis/medication risk. | K3: https://www.hhs.gov/hipaa/for-professionals/special-topics/de-identification/index.html
A4: Medical Record / Clinical Note | B4: Treating Provider Name / NPI Number | C4: Treating Provider Name / NPI Number | D4: Direct Identifier | E4: MEDIUM | F4: Discloses the treating clinician; can support social engineering against the practice, lower risk to the patient directly. | G4: HIPAA Privacy Rule | H4: Company policy evidence not supplied. | I4: REGULATION | J4: NPI is a public NPPES-registry identifier for the provider, not the patient, so patient-privacy impact is indirect; still useful context for record completeness. | K4: https://www.hhs.gov/hipaa/for-professionals/special-topics/de-identification/index.html
A5: Medical Record / Clinical Note | B5: Geographic Subdivision Smaller Than State (ZIP) | C5: Geographic Subdivision Smaller Than State (ZIP) | D5: Direct Identifier | E5: LOW | F5: Low standalone risk; becomes meaningful re-identification risk only in small-population geographies or combined with other quasi-identifiers. | G5: HIPAA Privacy Rule | H5: Company policy evidence not supplied. | I5: REGULATION | J5: Explicitly listed in HIPAA Safe Harbor, with a carve-out allowing the first three digits of a ZIP code if the associated population exceeds 20,000. Relevant primarily for de-identification workflows. | K5: https://www.hhs.gov/hipaa/for-professionals/special-topics/de-identification/index.html
A6: Medical Record / Clinical Note | B6: Age Over 89 (HIPAA Safe Harbor Threshold) | C6: Age Over 89 (HIPAA Safe Harbor Threshold) | D6: Direct Identifier | E6: LOW | F6: Low standalone risk; HIPAA requires ages over 89 to be aggregated into a single category to prevent re-identification of a small cohort. | G6: HIPAA Privacy Rule | H6: Company policy evidence not supplied. | I6: REGULATION | J6: Explicit Safe Harbor rule for the narrow band of very-elderly patients. General age fields for patients 89 and under are lower priority and can typically be treated as DROP unless bundled with DOB. | K6: https://www.hhs.gov/hipaa/for-professionals/special-topics/de-identification/index.html
A7: Medical Record / Clinical Note | B7: Signature | C7: Signature | D7: Direct Identifier | E7: MEDIUM | F7: Enables forgery of authorization for treatment or disclosure. | G7: HIPAA Privacy Rule | H7: Company policy evidence not supplied. | I7: REGULATION | J7: Evidence of patient/provider authorization; moderate standalone breach impact. | K7: https://www.hhs.gov/hipaa/for-professionals/special-topics/de-identification/index.html
A8: Lab Report / Pathology Report | B8: Lab Test Result / Value | C8: Lab Test Result / Value | D8: Health/Clinical Data | E8: MEDIUM | F8: Discloses physiological/health status; moderate standalone risk, higher when linked to identity. | G8: HIPAA Privacy Rule | H8: Company policy evidence not supplied. | I8: REGULATION | J8: Content-based PHI; classified NICE_TO_HAVE because raw numeric values carry less direct re-identification power than the diagnosis they support. | K8: https://www.hhs.gov/hipaa/for-professionals/special-topics/de-identification/index.html
A9: Lab Report / Pathology Report | B9: Treating Provider Name / NPI Number | C9: Treating Provider Name / NPI Number | D9: Direct Identifier | E9: MEDIUM | F9: Discloses the treating clinician; can support social engineering against the practice, lower risk to the patient directly. | G9: HIPAA Privacy Rule | H9: Company policy evidence not supplied. | I9: REGULATION | J9: NPI is a public NPPES-registry identifier for the provider, not the patient, so patient-privacy impact is indirect; still useful context for record completeness. | K9: https://www.hhs.gov/hipaa/for-professionals/special-topics/de-identification/index.html
A10: Prescription | B10: Treating Provider Name / NPI Number | C10: Treating Provider Name / NPI Number | D10: Direct Identifier | E10: MEDIUM | F10: Discloses the treating clinician; can support social engineering against the practice, lower risk to the patient directly. | G10: HIPAA Privacy Rule | H10: Company policy evidence not supplied. | I10: REGULATION | J10: NPI is a public NPPES-registry identifier for the provider, not the patient, so patient-privacy impact is indirect; still useful context for record completeness. | K10: https://www.hhs.gov/hipaa/for-professionals/special-topics/de-identification/index.html
A11: Prescription | B11: Signature | C11: Signature | D11: Direct Identifier | E11: MEDIUM | F11: Enables forgery of authorization for treatment or disclosure. | G11: HIPAA Privacy Rule | H11: Company policy evidence not supplied. | I11: REGULATION | J11: Evidence of patient/provider authorization; moderate standalone breach impact. | K11: https://www.hhs.gov/hipaa/for-professionals/special-topics/de-identification/index.html
A12: Discharge Summary | B12: Procedure Code / Description | C12: Procedure Code / Description | D12: Health/Clinical Data | E12: MEDIUM | F12: Discloses treatment history; can imply a condition (re-identification risk) and support insurance fraud. | G12: HIPAA Privacy Rule | H12: Company policy evidence not supplied. | I12: REGULATION | J12: Content-based PHI; lower standalone severity than an explicit diagnosis but still identifies care received. | K12: https://www.hhs.gov/hipaa/for-professionals/special-topics/de-identification/index.html
... A48: Employee Record / HR Application | B48: Employee ID Number | C48: Employee ID Number | D48: Direct Identifier | E48: LOW | F48: Links records to a specific employee; lower standalone fraud risk than a government ID or SSN. | G48: GDPR Art. 4 / India DPDP Act, 2023 | H48: Company policy evidence not supplied. | I48: REGULATION | J48: Internal identifier; meaningful primarily as a linkage key to other, higher-risk HR data. | K48: https://eur-lex.europa.eu/eli/reg/2016/679/art_4/par_1/oj
A49: Employee Record / HR Application | B49: Disciplinary Action Detail | C49: Disciplinary Action Detail | D49: HR Sensitive Data | E49: MEDIUM | F49: Reputational and employment harm; could affect future employment prospects if leaked. | G49: No specific statutory citation in the supplied source set | H49: Company policy evidence not supplied. | I49: BUSINESS_RISK | J49: Included on employment/reputational risk grounds; no regulation in the supplied source set enumerates this specifically.
A50: Employee Record / HR Application | B50: Performance Rating / Review Content | C50: Performance Rating / Review Content | D50: HR Sensitive Data | E50: MEDIUM | F50: Reputational and employment harm if disclosed to unauthorized parties (e.g., future employers, colleagues). | G50: No specific statutory citation in the supplied source set | H50: Company policy evidence not supplied. | I50: BUSINESS_RISK | J50: No regulation in the supplied source set specifically enumerates performance-review content; classified on employment/reputational risk grounds.
A51: Offer Letter / Employment Contract | B51: Salary / Compensation Amount | C51: Salary / Compensation Amount | D51: Financial Data | E51: MEDIUM | F51: Discloses financial standing; supports targeted scams and workplace-privacy harm. | G51: GDPR Art. 4 / India DPDP Act, 2023 | H51: Company policy evidence not supplied. | I51: REGULATION | J51: Personal financial data tied to an identifiable employee; sensitive but lower breach severity than an account number or SSN. | K51: https://eur-lex.europa.eu/eli/reg/2016/679/art_4/par_1/oj
A52: Offer Letter / Employment Contract | B52: Employee ID Number | C52: Employee ID Number | D52: Direct Identifier | E52: LOW | F52: Links records to a specific employee; lower standalone fraud risk than a government ID or SSN. | G52: GDPR Art. 4 / India DPDP Act, 2023 | H52: Company policy evidence not supplied. | I52: REGULATION | J52: Internal identifier; meaningful primarily as a linkage key to other, higher-risk HR data. | K52: https://eur-lex.europa.eu/eli/reg/2016/679/art_4/par_1/oj
A53: Offer Letter / Employment Contract | B53: Signature | C53: Signature | D53: Direct Identifier | E53: MEDIUM | F53: Enables forgery of employment-related authorization. | G53: GDPR Art. 4 / India DPDP Act, 2023 | H53: Company policy evidence not supplied. | I53: REGULATION | J53: Evidence of employee/employer acknowledgment. | K53: https://eur-lex.europa.eu/eli/reg/2016/679/art_4/par_1/oj
A54: Benefits / Performance / Disciplinary Document | B54: Employee ID Number | C54: Employee ID Number | D54: Direct Identifier | E54: LOW | F54: Links records to a specific employee; lower standalone fraud risk than a government ID or SSN. | G54: GDPR Art. 4 / India DPDP Act, 2023 | H54: Company policy evidence not supplied. | I54: REGULATION | J54: Internal identifier; meaningful primarily as a linkage key to other, higher-risk HR data. | K54: https://eur-lex.europa.eu/eli/reg/2016/679/art_4/par_1/oj
A55: Benefits / Performance / Disciplinary Document | B55: Performance Rating / Review Content | C55: Performance Rating / Review Content | D55: HR Sensitive Data | E55: MEDIUM | F55: Reputational and employment harm if disclosed to unauthorized parties (e.g., future employers, colleagues). | G55: No specific statutory citation in the supplied source set | H55: Company policy evidence not supplied. | I55: BUSINESS_RISK | J55: No regulation in the supplied source set specifically enumerates performance-review content; classified on employment/reputational risk grounds.
A56: Benefits / Performance / Disciplinary Document | B56: Disciplinary Action Detail | C56: Disciplinary Action Detail | D56: HR Sensitive Data | E56: MEDIUM | F56: Reputational and employment harm; could affect future employment prospects if leaked. | G56: No specific statutory citation in the supplied source set | H56: Company policy evidence not supplied. | I56: BUSINESS_RISK | J56: Included on employment/reputational risk grounds; no regulation in the supplied source set enumerates this specifically.
A57: Resume / CV | B57: Phone Number | C57: Phone Number | D57: Direct Identifier | E57: LOW | F57: Enables phishing/social engineering targeting the employee. | G57: GDPR Art. 4 / India DPDP Act, 2023 | H57: Company policy evidence not supplied. | I57: REGULATION | J57: Standard HR contact field. | K57: https://eur-lex.europa.eu/eli/reg/2016/679/art_4/par_1/oj
A58: Resume / CV | B58: Email Address | C58: Email Address | D58: Direct Identifier | E58: LOW | F58: Enables phishing and account-targeting against the employee. | G58: GDPR Art. 4 / India DPDP Act, 2023 | H58: Company policy evidence not supplied. | I58: REGULATION | J58: Standard HR contact field. | K58: https://eur-lex.europa.eu/eli/reg/2016/679/art_4/par_1/oj
A59: Identity Document (Passport / Driver License / National ID / Visa) | B59: Vehicle Identifier / License Plate Number | C59: Vehicle Identifier / License Plate Number | D59: Quasi-Identifier | E59: MEDIUM | F59: Traceable to a registered owner; supports physical tracking/stalking risk but generally lower direct fraud risk than a government ID. | G59: GDPR Art. 4 / NIST SP 800-122 | H59: Company policy evidence not supplied. | I59: REGULATION | J59: Not explicitly enumerated by HIPAA/PCI; included on a risk basis because a plate/VIN is reasonably linkable to an identifiable individual. | K59: https://eur-lex.europa.eu/eli/reg/2016/679/art_4/par_1/oj
A60: AML Document | B60: Transaction History / Amounts | C60: Transaction History / Amounts | D60: Financial Data | E60: LOW | F60: Discloses spending behavior/financial profile; privacy-relevant but not independently exploitable without account credentials. | G60: GDPR Art. 4 | H60: Company policy evidence not supplied. | I60: REGULATION | J60: Behavioral/financial-profile data; meaningful for privacy but secondary to the account and card identifiers themselves. | K60: https://eur-lex.europa.eu/eli/reg/2016/679/art_4/par_1/oj
A61: AML Document | B61: Case / Docket / Reference Number | C61: Case / Docket / Reference Number | D61: Administrative Identifier | E61: MEDIUM | F61: Links an individual to a specific legal or regulatory matter, which can itself be sensitive (e.g., litigation, AML case). | G61: No specific statutory citation in the supplied source set | H61: Company policy evidence not supplied. | I61: SECURITY_RISK | J61: No regulation in the supplied source set enumerates case/matter numbers directly; included on risk-based grounds because it links a person to a specific proceeding.
A62: Credential & Secrets Document (API keys, tokens, passwords) | B62: Username / Login ID | C62: Username / Login ID | D62: Security Credential | E62: MEDIUM | F62: Enables targeted credential-stuffing and account-targeting attacks, especially paired with a password. | G62: GDPR Art. 32 / GDPR Art. 4 | H62: Company policy evidence not supplied. | I62: REGULATION | J62: Low standalone risk; meaningful mainly in combination with a captured password/token. | K62: https://eur-lex.europa.eu/eli/reg/2016/679/art_32/oj
A63: Credential & Secrets Document (API keys, tokens, passwords) | B63: Session ID / Auth Cookie | C63: Session ID / Auth Cookie | D63: Security Credential — Online Identifier | E63: MEDIUM | F63: Enables session hijacking while the session remains valid. | G63: GDPR Art. 4 | H63: Company policy evidence not supplied. | I63: REGULATION | J63: GDPR Art. 4 explicitly includes online identifiers (such as cookie IDs) within the definition of personal data. | K63: https://eur-lex.europa.eu/eli/reg/2016/679/art_4/par_1/oj
A64: System Log / Incident Report / Security Report | B64: IP Address | C64: IP Address | D64: Online Identifier | E64: MEDIUM | F64: Supports device/location tracking and can enable targeted network attacks in a security-log context. | G64: GDPR Art. 4 | H64: Company policy evidence not supplied. | I64: REGULATION | J64: GDPR explicitly treats an IP address as personal data when linkable to an individual; classified NICE_TO_HAVE since standalone risk is moderate outside a security-incident context. | K64: https://eur-lex.europa.eu/eli/reg/2016/679/art_4/par_1/oj
A65: System Log / Incident Report / Security Report | B65: Device Identifier / MAC Address | C65: Device Identifier / MAC Address | D65: Online Identifier | E65: LOW | F65: Supports device-level tracking; moderate risk mainly in combination with other identifiers. | G65: GDPR Art. 4 | H65: Company policy evidence not supplied. | I65: REGULATION | J65: GDPR's definition of personal data extends to device identifiers linkable to a person; standalone impact is lower than an account credential. | K65: https://eur-lex.europa.eu/eli/reg/2016/679/art_4/par_1/oj
A66: System Log / Incident Report / Security Report | B66: Username / Login ID | C66: Username / Login ID | D66: Security Credential | E66: MEDIUM | F66: Enables targeted credential-stuffing and account-targeting attacks, especially paired with a password. | G66: GDPR Art. 32 / GDPR Art. 4 | H66: Company policy evidence not supplied. | I66: REGULATION | J66: Low standalone risk; meaningful mainly in combination with a captured password/token. | K66: https://eur-lex.europa.eu/eli/reg/2016/679/art_32/oj
A67: System Log / Incident Report / Security Report | B67: Session ID / Auth Cookie | C67: Session ID / Auth Cookie | D67: Security Credential — Online Identifier | E67: MEDIUM | F67: Enables session hijacking while the session remains valid. | G67: GDPR Art. 4 | H67: Company policy evidence not supplied. | I67: REGULATION | J67: GDPR Art. 4 explicitly includes online identifiers (such as cookie IDs) within the definition of personal data. | K67: https://eur-lex.europa.eu/eli/reg/2016/679/art_4/par_1/oj
A68: System Log / Incident Report / Security Report | B68: Email Address | C68: Email Address | D68: Direct Identifier | E68: MEDIUM | F68: Links a logged event to a specific mailbox/identity for follow-on phishing. | G68: GDPR Art. 32 / NIST SP 800-122 | H68: Company policy evidence not supplied. | I68: REGULATION | J68: Frequently present in authentication and application logs. | K68: https://eur-lex.europa.eu/eli/reg/2016/679/art_32/oj
A69: Contract / NDA / Legal Agreement | B69: Street / Mailing Address | C69: Street / Mailing Address | D69: Direct Identifier | E69: MEDIUM | F69: Discloses a party's residence/place of business tied to a legal matter. | G69: GDPR Art. 4 / NIST SP 800-122 | H69: Company policy evidence not supplied. | I69: REGULATION | J69: Commonly present in contracts and filings to identify parties. | K69: https://eur-lex.europa.eu/eli/reg/2016/679/art_4/par_1/oj
A70: Litigation Document / Regulatory Filing / Compliance Document | B70: Case / Docket / Reference Number | C70: Case / Docket / Reference Number | D70: Administrative Identifier | E70: MEDIUM | F70: Links an individual to a specific legal or regulatory matter, which can itself be sensitive (e.g., litigation, AML case). | G70: No specific statutory citation in the supplied source set | H70: Company policy evidence not supplied. | I70: SECURITY_RISK | J70: No regulation in the supplied source set enumerates case/matter numbers directly; included on risk-based grounds because it links a person to a specific proceeding.
A71: Litigation Document / Regulatory Filing / Compliance Document | B71: Street / Mailing Address | C71: Street / Mailing Address | D71: Direct Identifier | E71: MEDIUM | F71: Discloses a party's residence/place of business tied to a legal matter. | G71: GDPR Art. 4 / NIST SP 800-122 | H71: Company policy evidence not supplied. | I71: REGULATION | J71: Commonly present in contracts and filings to identify parties. | K71: https://eur-lex.europa.eu/eli/reg/2016/679/art_4/par_1/oj
A72: Email / Letter / General Form / Scanned Document | B72: Email Address | C72: Email Address | D72: Direct Identifier | E72: LOW | F72: Enables phishing, spam, and account-targeting. | G72: GDPR Art. 4 / India DPDP Act, 2023 | H72: Company policy evidence not supplied. | I72: REGULATION | J72: Common correspondence field. | K72: https://eur-lex.europa.eu/eli/reg/2016/679/art_4/par_1/oj
A73: Email / Letter / General Form / Scanned Document | B73: Phone Number | C73: Phone Number | D73: Direct Identifier | E73: LOW | F73: Enables phishing, spam, and social engineering. | G73: GDPR Art. 4 / India DPDP Act, 2023 | H73: Company policy evidence not supplied. | I73: REGULATION | J73: Common correspondence field. | K73: https://eur-lex.europa.eu/eli/reg/2016/679/art_4/par_1/oj
A74: Email / Letter / General Form / Scanned Document | B74: Street / Mailing Address | C74: Street / Mailing Address | D74: Direct Identifier | E74: MEDIUM | F74: Discloses residence; moderate risk on its own, higher when combined with a name. | G74: GDPR Art. 4 / India DPDP Act, 2023 | H74: Company policy evidence not supplied. | I74: REGULATION | J74: Common correspondence field. | K74: https://eur-lex.europa.eu/eli/reg/2016/679/art_4/par_1/oj
A75: Email / Letter / General Form / Scanned Document | B75: Signature | C75: Signature | D75: Direct Identifier | E75: LOW | F75: Low standalone risk; relevant mainly as forgery material in combination with other data. | G75: GDPR Art. 4 / India DPDP Act, 2023 | H75: Company policy evidence not supplied. | I75: REGULATION | J75: Present in general correspondence and forms. | K75: https://eur-lex.europa.eu/eli/reg/2016/679/art_4/par_1/oj

Sheet Drop_Entities
A1: Document Type | B1: Entity | C1: Canonical Entity | D1: Drop Reason | E1: Why It Should Not Be a Target | F1: Potential False Positive Source | G1: Evidence Checked | H1: Notes
A2: Lab Report / Pathology Report | B2: Medical Equipment/Instrument Serial Number | C2: Medical Equipment/Instrument Serial Number | D2: Low-value technical field | E2: Asset/equipment identifier, not a data-subject identifier. Not part of the HIPAA Safe Harbor identifier list (the list covers device identifiers implanted in/on the patient, not lab/imaging instruments). Frequent false-positive source when detectors key on "serial number" patterns. | F2: Regex/NER models keying on generic "serial number" / technical-identifier patterns unrelated to a data subject.
A3: Imaging / Radiology Report | B3: CT Number / Imaging Technical Parameter | C3: CT Number / Imaging Technical Parameter | D3: Low-value technical field | E3: Purely technical imaging-physics value (e.g., Hounsfield units); not linked to identity or a protected health status on its own, and highly dependency/vendor-specific. Detecting it produces noise without privacy benefit. | F3: Generic NER/pattern-matching models over-triggering on this field without contextual filtering.
A4: Imaging / Radiology Report | B4: Medical Equipment/Instrument Serial Number | C4: Medical Equipment/Instrument Serial Number | D4: Low-value technical field | E4: Asset/equipment identifier, not a data-subject identifier. Not part of the HIPAA Safe Harbor identifier list (the list covers device identifiers implanted in/on the patient, not lab/imaging instruments). Frequent false-positive source when detectors key on "serial number" patterns. | F4: Regex/NER models keying on generic "serial number" / technical-identifier patterns unrelated to a data subject.
A5: Summary of Benefits and Coverage (SBC) | B5: Insurer / Carrier Name | C5: Company / Employer Name | D5: No meaningful privacy/security basis established | E5: Business entity name identifying the insurer that issued the SBC, not personal data about the plan member. Present on every copy of the template regardless of enrollee. | F5: Rule/keyword detectors matching structural or label text (e.g., field labels, page headers/footers) rather than actual data values. | G5: N/A | H5: Frequent false-positive source for ORG-NER models scanning benefits documents.
A6: Summary of Benefits and Coverage (SBC) | B6: Plan Name / Tier (e.g., "Gold PPO 500") | C6: Plan Name | D6: No meaningful privacy/security basis established | E6: Product/marketing designation for the coverage tier; describes a plan design, not an individual. | F6: Generic NER/pattern-matching models over-triggering on this field without contextual filtering. | G6: N/A
A7: Summary of Benefits and Coverage (SBC) | B7: Coverage Example Scenario (fictional patient, e.g., "Peg is Having a Baby") | C7: Coverage Example Scenario | D7: No meaningful privacy/security basis established | E7: The federally-mandated SBC template uses standardized hypothetical patient scenarios to illustrate cost-sharing; these are not real individuals and carry no privacy value. A detector that fires on the fictional name here is a false positive and should be actively suppressed for this document type. | F7: Rule/keyword detectors matching structural or label text (e.g., field labels, page headers/footers) rather than actual data values. | G7: N/A | H7: Explicitly flagged so pipeline tuning does not mistake the fictional scenario name for a MUST_HAVE entity.
A8: Summary of Benefits and Coverage (SBC) | B8: Deductible / Copay / Coinsurance Amount | C8: Cost-Sharing Amount | D8: No meaningful privacy/security basis established | E8: Plan design terms that apply to every enrollee in the plan/tier; not a fact about a specific identifiable individual's finances (distinct from an individual's actual billed/paid amount on an EOB). | F8: Generic NER/pattern-matching models over-triggering on this field without contextual filtering. | G8: N/A | H8: Contrast with EOB "Patient Responsibility" amount, which IS individual-specific and is classified separately under the EOB document type.
A9: Health Insurance Policy / Benefits Document | B9: Plan Benefit Schedule / Coverage Tier Description | C9: Plan Name | D9: No meaningful privacy/security basis established | E9: Describes the product/plan design purchased, not a fact about the individual beyond their choice of plan; product-level boilerplate repeated across every member on that plan. | F9: Rule/keyword detectors matching structural or label text (e.g., field labels, page headers/footers) rather than actual data values. | G9: N/A
A10: Health Insurance Policy / Benefits Document | B10: Insurer Name / Logo / Customer Service Number | C10: Company / Employer Name | D10: No meaningful privacy/security basis established | E10: The insurer's own organizational identity and support contact info, not personal data about the member. | F10: Organization-NER (ORG) models that do not distinguish a business/institutional name from a personal name. | G10: N/A
A11: Medical Appointment / Appointment Reminder | B11: Appointment Confirmation / Booking Reference Number | C11: Booking Reference Number | D11: Dependency-specific field | E11: Internal scheduling-system reference number; useful for operational lookups but, standing alone, does not identify the patient or disclose health information. Distinguish from MRN, which does carry identifier status. | F11: Pattern-matching detectors that fire on any alphanumeric code near commercial/administrative keywords. | G11: N/A | H11: Frequent false-positive source when detectors match any alphanumeric code near the word "confirmation."
A12: Medical Appointment / Appointment Reminder | B12: Clinic General Address / Directions | C12: Facility Address | D12: No meaningful privacy/security basis established | E12: The facility's own public-facing address, not the patient's personal information. Distinguish from a sensitive department/specialty name at the same facility, which IS classified MUST_HAVE above. | F12: Generic NER/pattern-matching models over-triggering on this field without contextual filtering. | G12: N/A
A13: Healthcare Data Breach Notification Letter | B13: Breach Response Toll-Free Number / Organization Contact Info | C13: Organization Contact Info | D13: No meaningful privacy/security basis established | E13: The notifying organization's own support contact channel, identical across every recipient of the mass mailing; not personal data about the affected individual. | F13: Organization-NER (ORG) models that do not distinguish a business/institutional name from a personal name. | G13: N/A
A14: Healthcare Data Breach Notification Letter | B14: Covered Entity / Organization Name & Letterhead | C14: Company / Employer Name | D14: No meaningful privacy/security basis established | E14: Business identity of the notifying covered entity; not personal data about the recipient. | F14: Organization-NER (ORG) models that do not distinguish a business/institutional name from a personal name. | G14: N/A
A15: Healthcare Data Breach Notification Letter | B15: Standard Regulatory Notice Boilerplate (state AG rights language, HHS complaint instructions) | C15: Boilerplate / Disclaimer Text | D15: Template/header rather than sensitive value | E15: Standardized legal-notice language identical across every recipient's letter; not personal data and a common false-positive source for generic-form-language detectors. | F15: Rule/keyword detectors matching structural or label text (e.g., field labels, page headers/footers) rather than actual data values. | G15: N/A
A16: Payment Document / Receipt | B16: Merchant / Vendor Name | C16: Merchant / Vendor Name | D16: No meaningful privacy/security basis established | E16: Business/organizational data, not personal data about the document's data subject. High false-positive source if a detector flags any organization name as PII. | F16: Organization-NER (ORG) models that do not distinguish a business/institutional name from a personal name.
A17: Payment Document / Receipt | B17: Invoice Number | C17: Invoice Number | D17: Dependency-specific field | E17: Operational document identifier with negligible standalone privacy/breach impact. | F17: Pattern-matching detectors that fire on any alphanumeric code near commercial/administrative keywords.
A18: Payment Document / Receipt | B18: Line-item Product/Service Description | C18: Line-item Product/Service Description | D18: No meaningful privacy/security basis established | E18: Commercial content unrelated to personal-data protection goals; frequent false-positive source for generic NER models. | F18: Generic NER/pattern-matching models over-triggering on this field without contextual filtering.
A19: Invoice / Purchase Order | B19: Company / Employer Name | C19: Company / Employer Name | D19: No meaningful privacy/security basis established | E19: Business entity name, not personal data by itself under any of the reviewed frameworks; the organization's own identity is not the protected data subject. | F19: Organization-NER (ORG) models that do not distinguish a business/institutional name from a personal name.
A20: Invoice / Purchase Order | B20: Invoice Number | C20: Invoice Number | D20: Dependency-specific field | E20: Operational document identifier with negligible standalone privacy/breach impact. | F20: Pattern-matching detectors that fire on any alphanumeric code near commercial/administrative keywords.
A21: Invoice / Purchase Order | B21: Purchase Order Number | C21: Purchase Order Number | D21: No meaningful privacy/security basis established | E21: Operational/business identifier with no meaningful privacy/security exposure. | F21: Organization-NER (ORG) models that do not distinguish a business/institutional name from a personal name.
A22: Invoice / Purchase Order | B22: Line-item Product/Service Description | C22: Line-item Product/Service Description | D22: No meaningful privacy/security basis established | E22: Commercial content unrelated to personal-data protection goals; frequent false-positive source for generic NER models. | F22: Generic NER/pattern-matching models over-triggering on this field without contextual filtering.
A23: Tax Document | B23: Company / Employer Name | C23: Company / Employer Name | D23: No meaningful privacy/security basis established | E23: Business entity name, not personal data by itself under any of the reviewed frameworks; the organization's own identity is not the protected data subject. | F23: Organization-NER (ORG) models that do not distinguish a business/institutional name from a personal name.
A24: Payroll / Salary Document | B24: Company / Employer Name | C24: Company / Employer Name | D24: No meaningful privacy/security basis established | E24: Business entity name, not personal data by itself under any of the reviewed frameworks; the organization's own identity is not the protected data subject. | F24: Organization-NER (ORG) models that do not distinguish a business/institutional name from a personal name.
A25: Offer Letter / Employment Contract | B25: Job Title | C25: Job Title | D25: No meaningful privacy/security basis established | E25: A job title alone does not meaningfully identify or expose sensitive information about a specific person; treated as low-value noise unless the role itself is exceptionally rare within a small organization. | F25: Organization-NER (ORG) models that do not distinguish a business/institutional name from a personal name.
A26: Offer Letter / Employment Contract | B26: Company / Employer Name | C26: Company / Employer Name | D26: No meaningful privacy/security basis established | E26: Business entity name, not personal data by itself under any of the reviewed frameworks; the organization's own identity is not the protected data subject. | F26: Organization-NER (ORG) models that do not distinguish a business/institutional name from a personal name.
A27: Resume / CV | B27: Job Title | C27: Job Title | D27: No meaningful privacy/security basis established | E27: A job title alone does not meaningfully identify or expose sensitive information about a specific person; treated as low-value noise unless the role itself is exceptionally rare within a small organization. | F27: Organization-NER (ORG) models that do not distinguish a business/institutional name from a personal name.
... A41: Email / Letter / General Form / Scanned Document | B41: Barcode / QR Code Internal Document ID | C41: Barcode / QR Code Internal Document ID | D41: No meaningful privacy/security basis established | E41: System-generated tracking artifact; not personal data unless independently decoded to reveal an identifier already captured elsewhere. | F41: Generic NER/pattern-matching models over-triggering on this field without contextual filtering.

Sheet Regulatory_Sources
A1: Regulation / Standard | B1: Jurisdiction | C1: Official Source | D1: Relevant Section | E1: What It Protects | F1: Relevant Entity Categories | G1: Notes
A2: HIPAA Privacy Rule — Minimum Necessary | B2: United States | C2: https://www.hhs.gov/hipaa/for-professionals/privacy/guidance/minimum-necessary-requirement/index.html | D2: Minimum Necessary Requirement | E2: Limits use/disclosure of PHI to the minimum necessary to accomplish the intended purpose. | F2: All PHI entities | G2: Governs how much PHI a workflow may access, not which identifiers are 'PHI' per se.
A3: HIPAA Privacy Rule — De-identification / 18 Identifiers | B3: United States | C3: https://www.hhs.gov/hipaa/for-professionals/special-topics/de-identification/index.html | D3: Safe Harbor method — 18 identifier categories | E3: Defines the identifiers that must be removed for health data to be considered de-identified. | F3: All HIPAA-listed direct identifiers (name, MRN, dates, geography, biometric, photo, etc.) | G3: Primary source for health-context MUST_HAVE classifications in this workbook.
A4: HIPAA Privacy Rule — Minimum Necessary FAQ | B4: United States | C4: https://www.hhs.gov/hipaa/for-professionals/faq/207/how-are-covered-entities-to-determine-what-is-minimum-necessary/index.html | D4: FAQ #207 | E4: Clarifies how covered entities determine minimum necessary PHI. | F4: All PHI entities | G4: Supporting guidance, not an independent identifier list.
A5: GDPR — Full Regulation | B5: European Union | C5: https://eur-lex.europa.eu/eli/reg/2016/679/oj | D5: Regulation (EU) 2016/679 | E5: General EU data-protection framework for personal data. | F5: All PII entities where an EU data subject is involved | G5: Applicability depends on whether the data subject/controller is within GDPR's territorial scope — confirm before applying.
A6: GDPR Art. 4 — Personal Data definition | B6: European Union | C6: https://eur-lex.europa.eu/eli/reg/2016/679/art_4/par_1/oj | D6: Article 4(1) | E6: Defines 'personal data', including online/device identifiers. | F6: Name, address, email, phone, IP address, device ID, session/cookie ID | G6: Used as the general-purpose personal-data citation for cross-context identifiers.
A7: GDPR Art. 5 — Principles / Data Minimisation | B7: European Union | C7: https://eur-lex.europa.eu/eli/reg/2016/679/art_5/oj | D7: Article 5 | E7: Requires personal data collected/processed to be adequate, relevant, and limited to what is necessary. | F7: Supports the DROP rationale for low-value/noisy entities | G7: Cited conceptually to justify suppressing low-value detections, not as a per-entity citation.
A8: GDPR Art. 9 — Special Categories | B8: European Union | C8: https://eur-lex.europa.eu/eli/reg/2016/679/art_9/oj | D8: Article 9(1) | E8: Prohibits processing of special-category data (health, biometric, genetic, racial/ethnic, religious, union, sex life/orientation) absent a lawful basis. | F8: Biometric ID, genetic info, race/ethnicity, religion, union membership, sexual orientation, disability | G8: Note: criminal-offense data is governed by Art. 10, not Art. 9 — see Notes on Criminal Record / Background Check rows.
A9: GDPR Art. 32 — Security of Processing | B9: European Union | C9: https://eur-lex.europa.eu/eli/reg/2016/679/art_32/oj | D9: Article 32 | E9: Requires appropriate technical/organizational security measures for personal data. | F9: Passwords, API keys, tokens, private keys, security Q&A, OTP/MFA | G9: Primary basis for credential/security-entity classifications.
A10: PCI DSS | B10: Global (any entity handling payment cards) | C10: https://www.pcisecuritystandards.org/standards/pci-dss/ | D10: PCI Data Security Standard, current version | E10: Cardholder data and sensitive authentication data across the payment card lifecycle. | F10: PAN, expiry, cardholder name, CVV, PIN, track data | G10: Industry standard/contractual control, not a statute.
A11: PCI DSS FAQ — Cardholder/Payment Data | B11: Global | C11: https://www.pcisecuritystandards.org/faqs/1335/ | D11: FAQ #1335 | E11: Clarifies scope of cardholder data (PAN, expiry, cardholder name, service code). | F11: Card PAN, card expiry, cardholder name
A12: PCI DSS FAQ — Sensitive Authentication Data | B12: Global | C12: https://www.pcisecuritystandards.org/faqs/1533/ | D12: FAQ #1533 | E12: Defines SAD (full track data, CVV/CVC, PIN/PIN block) — must not be stored post-authorization. | F12: CVV, PIN, magnetic stripe/track data | G12: Highest-severity payment entities; presence post-authorization is a compliance violation.
A13: PCI DSS FAQ — Retention | B13: Global | C13: https://www.pcisecuritystandards.org/faqs/1318/ | D13: FAQ #1318 | E13: Clarifies permitted retention periods/practices for cardholder data. | F13: Card PAN, card expiry, cardholder name | G13: Relevant to retention-policy design, referenced for context.
A14: PCI DSS FAQ — Images Containing Cardholder Data | B14: Global | C14: https://www.pcisecuritystandards.org/faqs/1070/ | D14: FAQ #1070 | E14: Clarifies that scanned/photographed images of cards are in-scope cardholder data. | F14: Card PAN (scanned/imaged documents) | G14: Relevant to OCR/image-based detection pipelines specifically.
A15: NIST SP 800-122 — Guide to Protecting PII Confidentiality | B15: United States (federal risk-management guidance) | C15: https://csrc.nist.gov/pubs/sp/800/122/final | D15: Section 2.1 — PII definition & examples | E15: Provides a risk-based framework for identifying and protecting PII. | F15: SSN, passport number, driver's license, national ID, IP/device identifiers | G15: A standard/framework, not a binding statute — used as STANDARD/CONTROL basis.
A16: NIST PII Confidentiality Impact Level | B16: United States | C16: https://csrc.nist.gov/glossary/term/PII_Confidentiality_Impact_Level | D16: Glossary term | E16: Defines the Low/Moderate/High impact-level framework used to grade PII risk. | F16: Basis for Risk Level column methodology | G16: Used conceptually to support qualitative Risk Level assignment.
A17: NIST FIPS 199 | B17: United States | C17: https://csrc.nist.gov/pubs/fips/199/final | D17: Security categorization standard | E17: Standards for categorizing information/information systems by impact level. | F17: Basis for Risk Level column methodology | G17: Used conceptually to support qualitative Risk Level assignment.
A18: NIST Privacy Framework | B18: United States | C18: https://www.nist.gov/privacy-framework | D18: Framework overview | E18: Voluntary framework for managing privacy risk. | F18: General methodology reference | G18: Referenced for overall taxonomy methodology, not per-entity citations.
A19: FTC Safeguards Rule (GLBA) | B19: United States (financial institutions) | C19: https://www.ftc.gov/legal-library/browse/rules/safeguards-rule | D19: 16 CFR Part 314 | E19: Requires financial institutions to safeguard customer financial information. | F19: Bank account numbers, routing numbers, loan/investment account numbers, credit-related data | G19: Primary basis for financial-account MUST_HAVE classifications.
A20: FTC Safeguards Rule — Business Guidance | B20: United States | C20: https://www.ftc.gov/business-guidance/resources/ftc-safeguards-rule-what-your-business-needs-know | D20: Plain-language guidance | E20: Explains Safeguards Rule obligations in accessible terms. | F20: Financial account data generally | G20: Supporting guidance, not itself a separate legal requirement.
A21: Digital Personal Data Protection Act, 2023 (via MeitY) | B21: India | C21: https://www.meity.gov.in/ | D21: Act overview / MeitY portal | E21: India's general personal-data-protection statute. | F21: Aadhaar, PAN (India), and general PII where the data principal is in India | G21: Portal-level source; use alongside the DPDP Rules 2025 link for implementation detail.
A22: Digital Personal Data Protection Rules, 2025 | B22: India | C22: https://www.meity.gov.in/documents/act-and-policies/digital-personal-data-protection-rules-2025-gDOxUjMtQWa | D22: DPDP Rules, 2025 | E22: Implementation rules under the DPDP Act, 2023. | F22: Aadhaar, PAN (India), and general PII where the data principal is in India | G22: The Act does not enumerate a fixed identifier list the way HIPAA does — applicability is assessed via the 'personal data' definition, not a checklist.
A23: HIPAA Breach Notification Rule (45 CFR §164.400-414) — NOT in supplied source set | B23: United States | C23: Not supplied in this engagement's source list — see https://www.hhs.gov/hipaa/for-professionals/special-topics/de-identification/index.html for the related Safe Harbor identifier list that IS supplied | D23: N/A — flagged gap, not a verified citation | E23: Requires covered entities to notify affected individuals after a breach of unsecured PHI and to describe the PHI involved. | F23: Entities appearing in Healthcare Data Breach Notification Letter rows | G23: Referenced only in Notes/Rationale for context on Healthcare Data Breach Notification Letter rows; verify independently before relying on it as a compliance citation — it was not among the URLs supplied for this engagement.

Sheet Policy_Sources
A1: No company/client policy documents were supplied for this engagement.
A2: If a Data Classification Policy, PII/PHI Handling Policy, Information Security Policy, Data Retention Policy, Data Masking/Redaction Policy, DLP Policy, Access Control Policy, Incident Response Policy, Encryption Policy, or Confidential Data Policy is provided later, add rows to this sheet mapping each policy to the entity types and document types it governs, and update the 'Company Policy' / 'Policy Requirement' columns in Master_Entity_Policy accordingly.
A4: Policy Name | B4: Organization / Source | C4: Scope | D4: Relevant Data Categories | E4: Relevant Entity Types | F4: Source | G4: Notes
A5: Company policy evidence not supplied.

Sheet Entity_Canonicalization
A1: Raw Entity Name | B1: Canonical Entity | C1: Category | D1: Aliases | E1: Country | F1: Notes
A2: Full Name / Person Name | B2: Full Name / Person Name | C2: Direct Identifier | D2: Name; Patient Name; Full Legal Name; Customer Name; Employee Name; Insured Name | E2: Global | F2: Bucketed identifier — regulation basis varies by document context (see Master_Entity_Policy).
A3: Date of Birth | B3: Date of Birth | C3: Direct Identifier | D3: DOB; Birth Date; Date of birth | E3: Global | F3: Bucketed identifier — regulation basis varies by document context (see Master_Entity_Policy).
A4: Street / Mailing Address | B4: Street / Mailing Address | C4: Direct Identifier | D4: Address; Home Address; Mailing Address; Residential Address; Billing Address | E4: Global | F4: Bucketed identifier — regulation basis varies by document context (see Master_Entity_Policy).
A5: Phone Number | B5: Phone Number | C5: Direct Identifier | D5: Telephone Number; Mobile Number; Contact Number; Cell Phone | E5: Global | F5: Bucketed identifier — regulation basis varies by document context (see Master_Entity_Policy).
A6: Email Address | B6: Email Address | C6: Direct Identifier | D6: E-mail; Email ID; Email Address | E6: Global | F6: Bucketed identifier — regulation basis varies by document context (see Master_Entity_Policy).
A7: Signature | B7: Signature | C7: Direct Identifier | D7: Wet Signature; Digital Signature; E-Signature; Signature Block | E7: Global | F7: Bucketed identifier — regulation basis varies by document context (see Master_Entity_Policy).
A8: Medical Record Number (MRN) | B8: Medical Record Number (MRN) | C8: Direct Identifier | D8: MRN; Patient ID; Chart Number; Patient Account Number | E8: Global
A9: Health Plan Beneficiary/Member Number | B9: Health Plan Beneficiary/Member Number | C9: Direct Identifier | D9: Member ID; Beneficiary Number; Insurance Member Number; Subscriber ID | E9: Global
A10: Diagnosis / Medical Condition | B10: Diagnosis / Medical Condition | C10: Health/Clinical Data | D10: ICD Code; Condition; Clinical Diagnosis; Assessment | E10: Global
A11: Procedure Code / Description | B11: Procedure Code / Description | C11: Health/Clinical Data | D11: CPT Code; Procedure; Treatment Performed | E11: Global
A12: Medication / Prescription Detail | B12: Medication / Prescription Detail | C12: Health/Clinical Data | D12: Drug Name; Rx; Prescription; Dosage | E12: Global
A13: Lab Test Result / Value | B13: Lab Test Result / Value | C13: Health/Clinical Data | D13: Lab Value; Test Result; Specimen Result | E13: Global
A14: Clinical Notes / Narrative | B14: Clinical Notes / Narrative | C14: Health/Clinical Data | D14: Progress Note; SOAP Note; Physician Narrative | E14: Global
A15: Allergy Information | B15: Allergy Information | C15: Health/Clinical Data | D15: Allergies; Known Drug Allergies | E15: Global
A16: Immunization Record | B16: Immunization Record | C16: Health/Clinical Data | D16: Vaccination Record; Immunization History | E16: Global
A17: Mental / Behavioral Health Notes | B17: Mental / Behavioral Health Notes | C17: Health/Clinical Data — Heightened Sensitivity | D17: Psychiatric Note; Therapy Note; Behavioral Health Record | E17: Global
A18: Substance Use Disorder Treatment Info | B18: Substance Use Disorder Treatment Info | C18: Health/Clinical Data — Heightened Sensitivity | D18: SUD Treatment Record; Addiction Treatment Note | E18: Global | F18: 42 CFR Part 2 applicability not verified against an official source in this engagement's source set.
A19: HIV / STI Status | B19: HIV / STI Status | C19: Health/Clinical Data — Heightened Sensitivity | D19: HIV Status; STD Diagnosis; STI Result | E19: Global | F19: State-level HIV/STI confidentiality statutes not verified against an official source in this engagement's source set.
A20: Genetic / Genomic Information | B20: Genetic / Genomic Information | C20: Health/Clinical Data — Heightened Sensitivity | D20: Genetic Test Result; Genomic Data; DNA Test Result | E20: Global
A21: Treating Provider Name / NPI Number | B21: Treating Provider Name / NPI Number | C21: Direct Identifier | D21: Physician Name; NPI; Provider ID; Attending Physician | E21: Global
A22: Health Insurance Policy Number | B22: Health Insurance Policy Number | C22: Direct Identifier | D22: Policy Number; Health Plan ID | E22: Global
A23: Medical Claim Number | B23: Medical Claim Number | C23: Direct Identifier | D23: Claim ID; Claim Reference Number | E23: Global
A24: Imaging Study ID / Accession Number | B24: Imaging Study ID / Accession Number | C24: Direct Identifier | D24: Accession Number; Study ID | E24: Global
A25: CT Number / Imaging Technical Parameter | B25: CT Number / Imaging Technical Parameter | C25: Administrative/Structural Metadata | D25: CT Value; Hounsfield Unit; Scanner Technical Parameter | E25: Global
A26: Medical Equipment/Instrument Serial Number | B26: Medical Equipment/Instrument Serial Number | C26: Administrative/Structural Metadata | D26: Scanner Serial Number; Analyzer ID; Device Serial Number | E26: Global
A27: Geographic Subdivision Smaller Than State (ZIP) | B27: Geographic Subdivision Smaller Than State (ZIP) | C27: Direct Identifier | D27: ZIP Code; Postal Code; Geographic Subdivision | E27: Global
A28: Age Over 89 (HIPAA Safe Harbor Threshold) | B28: Age Over 89 (HIPAA Safe Harbor Threshold) | C28: Direct Identifier | D28: Age >89; Age 90+ | E28: Global
A29: Admission / Discharge / Service Date | B29: Admission / Discharge / Service Date | C29: Direct Identifier | D29: Date of Service; Admission Date; Discharge Date | E29: Global
A30: Photograph / Facial Image | B30: Photograph / Facial Image | C30: Direct Identifier / Biometric-Adjacent | D30: Patient Photo; ID Photo; Facial Image | E30: Global
A31: Biometric Identifier (fingerprint / retina / voiceprint) | B31: Biometric Identifier (fingerprint / retina / voiceprint) | C31: Sensitive/Special Category | D31: Fingerprint; Retina Scan; Voiceprint; Iris Scan | E31: Global
A32: Social Security Number (SSN) | B32: Social Security Number (SSN) | C32: Government Identifier | D32: SSN; Social Security No.; Social Security Number | E32: United States
A33: US Tax ID (EIN / ITIN) | B33: US Tax ID (EIN / ITIN) | C33: Government Identifier | D33: EIN; ITIN; Federal Tax ID | E33: United States | F33: IRS-specific citations (e.g., Publication 4812) were not in the supplied source set and are not cited here.
A34: Aadhaar Number (India) | B34: Aadhaar Number (India) | C34: Government Identifier | D34: Aadhaar; Aadhar Number; UID | E34: India | F34: Aadhaar is also separately governed by the Aadhaar Act, 2016, which was not in the supplied source set — verify that citation independently.
A35: Permanent Account Number — Income Tax (India) | B35: Permanent Account Number — Income Tax (India) | C35: Government Identifier | D35: PAN; Income Tax PAN; PAN Card Number | E35: India
A36: National / Government ID Number (Generic, non-US/non-India) | B36: National / Government ID Number (Generic, non-US/non-India) | C36: Government Identifier | D36: National ID; Government ID Number; Citizen ID | E36: Global
A37: Passport Number | B37: Passport Number | C37: Government Identifier | D37: Passport No.; Passport ID | E37: Global
A38: Driver's License Number | B38: Driver's License Number | C38: Government Identifier | D38: DL Number; Driving License Number | E38: Global
A39: Visa / Immigration Document Number | B39: Visa / Immigration Document Number | C39: Government Identifier | D39: Visa Number; Immigration Case Number | E39: Global
A40: Vehicle Identifier / License Plate Number | B40: Vehicle Identifier / License Plate Number | C40: Quasi-Identifier | D40: VIN; License Plate; Registration Number | E40: Global
A41: Bank Account Number | B41: Bank Account Number | C41: Financial Account Data | D41: Account Number; A/C No. | E41: Global
A42: Bank Routing / Sort Code | B42: Bank Routing / Sort Code | C42: Financial Account Data | D42: Routing Number; ABA Number; Sort Code; IFSC Code | E42: Global
A43: IBAN / SWIFT-BIC Code | B43: IBAN / SWIFT-BIC Code | C43: Financial Account Data | D43: IBAN; SWIFT Code; BIC | E43: Global
A44: Payment Card Number (PAN) | B44: Payment Card Number (PAN) | C44: Payment Card — Cardholder Data | D44: Credit Card Number; Debit Card Number; Card Number | E44: Global | F44: Disambiguate from India Income Tax PAN — see Entity_Canonicalization sheet.
A45: Card Expiration Date | B45: Card Expiration Date | C45: Payment Card — Cardholder Data | D45: Expiry Date; Exp Date; Valid Thru | E45: Global
A46: Cardholder Name | B46: Cardholder Name | C46: Payment Card — Cardholder Data | D46: Name on Card | E46: Global
A47: Card Verification Code (CVV/CVC/CID/CAV2) | B47: Card Verification Code (CVV/CVC/CID/CAV2) | C47: Payment Card — Sensitive Authentication Data | D47: CVV; CVC; CID; CAV2; Security Code | E47: Global
A48: PIN / PIN Block | B48: PIN / PIN Block | C48: Payment Card — Sensitive Authentication Data | D48: Card PIN; PIN Number; PIN Block | E48: Global
A49: Full Magnetic Stripe / Track Data | B49: Full Magnetic Stripe / Track Data | C49: Payment Card — Sensitive Authentication Data | D49: Track 1 Data; Track 2 Data; Magnetic Stripe Data | E49: Global
A50: Credit Score | B50: Credit Score | C50: Financial Account Data | D50: FICO Score; Credit Rating | E50: Global
A51: Loan / Mortgage Account Number | B51: Loan / Mortgage Account Number | C51: Financial Account Data | D51: Loan Number; Mortgage Account Number | E51: Global
A52: Investment / Brokerage Account Number | B52: Investment / Brokerage Account Number | C52: Financial Account Data | D52: Brokerage Account Number; Investment Account No. | E52: Global
A53: Salary / Compensation Amount | B53: Salary / Compensation Amount | C53: Financial Data | D53: Gross Salary; Net Pay; Annual Compensation | E53: Global
A54: Securities / Portfolio Holdings Detail | B54: Securities / Portfolio Holdings Detail | C54: Financial Data | D54: Holdings; Positions; Portfolio Statement Detail | E54: Global
A55: Transaction History / Amounts | B55: Transaction History / Amounts | C55: Financial Data | D55: Transaction Detail; Payment History; Statement Line Items | E55: Global
A56: Merchant / Vendor Name | B56: Merchant / Vendor Name | C56: Administrative/Structural Metadata | D56: Merchant; Vendor Name; Payee | E56: Global
... A75: Disciplinary Action Detail | B75: Disciplinary Action Detail | C75: HR Sensitive Data | D75: Disciplinary Record; Corrective Action Notice | E75: Global
A76: Background / Criminal Background Check Result | B76: Background / Criminal Background Check Result | C76: HR Sensitive Data | D76: Background Check Report; Background Screening Result | E76: Global | F76: Evidence gap: GDPR Art. 10 and US FCRA were not in the supplied source set; verify both independently before relying on this classification.
A77: Criminal Record / Conviction Data | B77: Criminal Record / Conviction Data | C77: HR Sensitive Data | D77: Conviction Record; Criminal History | E77: Global | F77: Evidence gap: GDPR Art. 10 not in the supplied source set; verify independently before relying on this classification.
A78: Trade Union Membership | B78: Trade Union Membership | C78: HR Sensitive Data — Special Category | D78: Union Member; Union Affiliation | E78: Global
A79: Religious Belief / Affiliation | B79: Religious Belief / Affiliation | C79: HR Sensitive Data — Special Category | D79: Religion; Religious Affiliation | E79: Global
A80: Racial or Ethnic Origin Data | B80: Racial or Ethnic Origin Data | C80: HR Sensitive Data — Special Category | D80: Race; Ethnicity | E80: Global
A81: Sexual Orientation / Gender Identity | B81: Sexual Orientation / Gender Identity | C81: HR Sensitive Data — Special Category | D81: Sexual Orientation; Gender Identity | E81: Global
A82: Disability Status | B82: Disability Status | C82: HR Sensitive Data | D82: Disability; Accommodation Request | E82: Global
A83: Job Title | B83: Job Title | C83: Administrative/Structural Metadata | D83: Position Title; Designation | E83: Global
A84: Case / Docket / Reference Number | B84: Case / Docket / Reference Number | C84: Administrative Identifier | D84: Case Number; Docket Number; Matter Reference | E84: Global
A85: Court / Jurisdiction Name | B85: Court / Jurisdiction Name | C85: Administrative/Structural Metadata | D85: Court Name; Venue | E85: Global
A86: Attorney-Client Privilege Notation | B86: Attorney-Client Privilege Notation | C86: Administrative/Structural Metadata | D86: Privileged & Confidential; Attorney Work Product | E86: Global
A87: Form / Template Field Label | B87: Form / Template Field Label | C87: Administrative/Structural Metadata | D87: Field Label; Form Header Label | E87: Global
A88: Page Number | B88: Page Number | C88: Administrative/Structural Metadata | D88: Page #; Pg. | E88: Global
A89: Boilerplate / Disclaimer Text | B89: Boilerplate / Disclaimer Text | C89: Administrative/Structural Metadata | D89: Legal Disclaimer; Standard Terms Boilerplate | E89: Global
... A92: Barcode / QR Code Internal Document ID | B92: Barcode / QR Code Internal Document ID | C92: Administrative/Structural Metadata | D92: Barcode Value; QR Payload | E92: Global
A93: PAN (ambiguous acronym) | B93: AMBIGUOUS — resolve by context | C93: Disambiguation | D93: PAN | E93: India (tax) vs. Global (payment) | F93: "PAN" means Income Tax Permanent Account Number in an Indian tax/KYC context, but Primary Account Number (payment card) in a payments context. Canonicalize using surrounding context, not the acronym alone — see 'Permanent Account Number — Income Tax (India)' vs. 'Payment Card Number (PAN)'.
A94: CVV family | B94: Card Verification Code (CVV/CVC/CID/CAV2) | C94: Payment Card — Sensitive Authentication Data | D94: CVV; CVC; CID; CAV2; Security Code; CVV2 | E94: Global | F94: All are network-specific names for the same card-verification-code concept — canonicalize to a single family.
A95: SSN family | B95: Social Security Number (SSN) | C95: Government Identifier | D95: SSN; Social Security No.; Social Security Number | E95: United States | F95: Do not conflate with a generic 'National ID Number' — SSN has a specific 9-digit US format and specific regulatory treatment.
A96: Booking Reference Number | B96: Booking Reference Number | C96: Administrative/Structural Metadata | D96: Confirmation Number; Appointment Reference; Scheduling ID | E96: Global (US healthcare-document context) | F96: Added for new document types (SBC, Health Insurance Policy/Benefits, Appointment Reminder, Breach Notification Letter); see Master_Entity_Policy for classification/regulatory basis.
A97: Breach Incident Description | B97: Breach Incident Description | C97: Administrative/Structural Metadata | D97: Incident Summary; What Happened Section | E97: Global (US healthcare-document context) | F97: Added for new document types (SBC, Health Insurance Policy/Benefits, Appointment Reminder, Breach Notification Letter); see Master_Entity_Policy for classification/regulatory basis.
A98: Breached Data Element Description | B98: Breached Data Element Description | C98: Health/Clinical Data | D98: Types of PHI Involved; Compromised Information Description | E98: Global (US healthcare-document context) | F98: Added for new document types (SBC, Health Insurance Policy/Benefits, Appointment Reminder, Breach Notification Letter); see Master_Entity_Policy for classification/regulatory basis.
A99: Cost-Sharing Amount | B99: Cost-Sharing Amount | C99: Administrative/Structural Metadata | D99: Deductible; Copay; Coinsurance; Out-of-Pocket Amount | E99: Global (US healthcare-document context) | F99: Added for new document types (SBC, Health Insurance Policy/Benefits, Appointment Reminder, Breach Notification Letter); see Master_Entity_Policy for classification/regulatory basis.
A100: Coverage Date | B100: Coverage Date | C100: Administrative Identifier | D100: Coverage Effective Date; Coverage Termination Date; Enrollment Date | E100: Global (US healthcare-document context) | F100: Added for new document types (SBC, Health Insurance Policy/Benefits, Appointment Reminder, Breach Notification Letter); see Master_Entity_Policy for classification/regulatory basis.
A101: Coverage Example Scenario | B101: Coverage Example Scenario | C101: Administrative/Structural Metadata | D101: Sample Patient Scenario; Illustrative Example | E101: Global (US healthcare-document context) | F101: Added for new document types (SBC, Health Insurance Policy/Benefits, Appointment Reminder, Breach Notification Letter); see Master_Entity_Policy for classification/regulatory basis.
A102: Department / Specialty Name | B102: Department / Specialty Name | C102: Health/Clinical Data | D102: Clinic Department; Medical Specialty; Service Line | E102: Global (US healthcare-document context) | F102: Added for new document types (SBC, Health Insurance Policy/Benefits, Appointment Reminder, Breach Notification Letter); see Master_Entity_Policy for classification/regulatory basis.
A103: Enrollment/Activation Code | B103: Enrollment/Activation Code | C103: Security Credential | D103: Credit Monitoring Code; Identity Protection Activation Code | E103: Global (US healthcare-document context) | F103: Added for new document types (SBC, Health Insurance Policy/Benefits, Appointment Reminder, Breach Notification Letter); see Master_Entity_Policy for classification/regulatory basis.
A104: Facility Address | B104: Facility Address | C104: Administrative/Structural Metadata | D104: Clinic Address; Practice Location Address | E104: Global (US healthcare-document context) | F104: Added for new document types (SBC, Health Insurance Policy/Benefits, Appointment Reminder, Breach Notification Letter); see Master_Entity_Policy for classification/regulatory basis.
... A108: Premium Amount | B108: Premium Amount | C108: Financial Data | D108: Monthly Premium; Premium Due | E108: Global (US healthcare-document context) | F108: Added for new document types (SBC, Health Insurance Policy/Benefits, Appointment Reminder, Breach Notification Letter); see Master_Entity_Policy for classification/regulatory basis.
